Workbook
Name Slicer_Channel: #N/A
Name Slicer_Country: #N/A
Name Slicer_months: #N/A
Name Slicer_ProductCategory: #N/A
Name Slicer_Region: #N/A
Name Slicer_Salesperson: #N/A

Sheet original_data
A1: OrderID | B1: OrderDate | C1: RequiredDate | D1: Region | E1: Country | F1: City | G1: CustomerSegment | H1: Channel | I1: Salesperson | J1: ProductCategory | K1: SKU | L1: UnitCost | M1: UnitPrice | N1: DiscountPct | O1: Quantity
A2: ORD-2024-275203 | B2: 45362 | C2: 45388 | D2: Africa | E2: Kenya | F2: Kisumu | G2: Corporate | H2: Retail | I2: C. Otieno | J2: Components | K2: CMP-8270 | L2: 279.24 | M2: 608.9 | N2: 0.112 | O2: 9
A3: ORD-2024-358795 | B3: 45588 | C3: 45587 | D3: Africa | E3: Nigeria | F3: Port Harcourt | G3: Education | H3: Online | I3: J. Njeri | J3: Printers | K3: PRN-9322 | L3: 1084.39 | M3: 759.33 | N3: 0.237 | O3: 31
A4: ORD-2023-373538 | B4: 44985 | C4: 45010 | D4: Africa | E4: Kenya | F4: Nairobi | G4: Corporate | H4: Retail | I4: I. Johnson | J4: Networking | K4: NET-9666 | L4: 1460.76 | M4: -30.66 | N4: 0.131 | O4: 12
A5: ORD-2025-168148 | B5: 45745 | C5: 45749 | D5: Africa | E5: Nigeria | F5: Lagos | G5: Non-Profit | H5: Marketplace | I5: G. Dubois | J5: Phones | K5: PHN-4556 | L5: 259.93 | M5: 255.94 | N5: 0.072 | O5: 22
A6: ORD-2023-824839 | B6: 45266 | C6: 45291 | D6: Asia | E6: Japan | F6: Osaka | G6: Consumer | H6: Retail | I6: L. Okafor | J6: Printers | K6: PRN-8041 | L6: 663.03 | M6: 813.51 | N6: 0.102 | O6: 15
A7: ORD-2023-723587 | B7: 44928 | C7: 44931 | D7: Americas | E7: Canada | F7: Toronto | G7: Corporate | H7: Distributor | I7: B. Chen | J7: Laptops | K7: LAP-8555 | L7: 315.87 | M7: 591.68 | N7: 0 | O7: 7
A8: ORD-2024-336584 | B8: 45653 | C8: 45671 | D8: Asia | E8: India | F8: Bengaluru | G8: Small Business | H8: Marketplace | I8: E. Garcia | J8: Monitors | K8: MON-8629 | L8: 586.07 | M8: 845.97 | N8: 0.147 | O8: 4
A9: ORD-2023-112666 | B9: 44941 | C9: 44939 | D9: Africa | E9: Nigeria | F9: Abuja | G9: Education | H9: Online | I9: O. Wang | J9: Printers | K9: PRN-6276 | L9: 28.38 | M9: 47.22 | N9: 0.194 | O9: 18
A10: ORD-2024-589570 | B10: 45416 | C10: 45441 | D10: Africa | E10: Nigeria | F10: Abuja | G10: Non-Profit | H10: Marketplace | I10: O. Wang | J10: Monitors | K10: MON-6892 | L10: 1295.34 | M10: 2530.81 | N10: 0.031 | O10: 6
A11: ORD-2025-997421 | B11: 45798 | C11: 45817 | D11: Americas | E11: Brazil | F11: São Paulo | G11: Non-Profit | H11: Online | I11: A. Patel | J11: Components | K11: CMP-3731 | L11: 1331.38 | M11: 2309.56 | N11: 0.149 | O11: 31
A12: ORD-2024-210687 | B12: 45319 | C12: 45331 | D12: Europe | E12: Germany | F12: Berlin | G12: Corporate | H12: Online | I12: G. Dubois | J12: Accessories | K12: ACC-7938 | L12: 644.17 | M12: 700.12 | N12: 0.006 | O12: 23
A13: ORD-2025-515515 | B13: 45660 | C13: 45680 | D13: Asia | E13: Japan | F13: Osaka | G13: Corporate | H13: Distributor | I13: F. Müller | J13: Phones | K13: PHN-7019 | L13: 908.6 | M13: 691.37 | N13: 0.25 | O13: 20
... A34: ORD-2025-474710 | B34: 45862 | C34: 45875 | D34: Africa | E34: South Africa | F34: Johannesburg | G34: Education | H34: Marketplace | I34: D. Smith | J34: Networking | K34: NET-7966 | L34: 1463.9 | M34: 2633.02 | N34: 0.084 | O34: 4
A35: ORD-2024-629525 | B35: 45400 | C35: 45420 | D35: Europe | E35: United Kingdom | F35: London | G35: Non-Profit | I35: D. Smith | J35: Laptops | K35: LAP-9932 | L35: 645.33 | M35: 1321.85 | N35: 0 | O35: 10
A36: ORD-2024-167215 | B36: 45527 | C36: 45525 | D36: Africa | E36: South Africa | F36: Johannesburg | G36: Education | H36: Retail | I36: E. Garcia | J36: Components | K36: CMP-1559 | L36: 1432.52 | M36: 3036.87 | N36: 0 | O36: 9
A37: ORD-2023-864121 | B37: 45012 | C37: 45038 | D37: Asia | E37: India | F37: Delhi | G37: Non-Profit | H37: Marketplace | I37: J. Njeri | J37: Printers | K37: PRN-4506 | L37: 178.53 | M37: 199.37 | N37: 0.101 | O37: 37
A38: ORD-2024-692673 | B38: 45358 | C38: 45376 | D38: Europe | E38: Germany | F38: Munich | G38: Corporate | H38: Online | I38: B. Chen | J38: Components | K38: CMP-7617 | L38: 712.84 | M38: 927.51 | N38: 0.243 | O38: 27
A39: ORD-2025-718992 | B39: 45832 | C39: 45848 | D39: Asia | E39: China | F39: Shanghai | G39: Enterprise | H39: Direct | I39: N. Brown | J39: Components | K39: CMP-8390 | L39: 757.19 | M39: 1735.41 | N39: 0.136 | O39: 8
A40: ORD-2024-599522 | B40: 45401 | C40: 45418 | D40: Africa | E40: Nigeria | F40: Port Harcourt | G40: Non-Profit | H40: Online | I40: A. Patel | J40: Printers | K40: PRN-7303 | L40: 865.33 | M40: 1395.64 | N40: 0.175 | O40: 13
A41: ORD-2023-651638 | B41: 45094 | C41: 45101 | D41: Americas | E41: USA | F41: San Francisco | G41: Corporate | H41: Retail | I41: I. Johnson | J41: Printers | K41: PRN-6536 | L41: 313.99 | M41: 454.42 | N41: 0.129 | O41: 9
A42: ORD-2024-635626 | B42: 45531 | C42: 45554 | D42: Europe | E42: Germany | F42: Berlin | G42: Small Business | H42: Direct | I42: D. Smith | J42: Monitors | K42: MON-9967 | L42: 1024.01 | M42: 1580.97 | N42: 0.037 | O42: 27
A43: ORD-2024-296582 | B43: 45302 | C43: 45324 | D43: Africa | E43: South Africa | F43: Durban | G43: Consumer | H43: Online | I43: K. Singh | J43: Networking | K43: NET-1412 | L43: 1206.2 | M43: 1759.79 | N43: 0 | O43: 6
A44: ORD-2024-998320 | B44: 45590 | C44: 45610 | D44: Africa | E44: Kenya | F44: Mombasa | G44: Corporate | H44: Direct | I44: H. Kim | J44: Printers | K44: PRN-3143 | L44: 1396.48 | M44: 3204.5 | N44: 0.318 | O44: 14
A45: ORD-2025-820255 | B45: 45806 | C45: 45828 | D45: Europe | E45: Germany | F45: Berlin | G45: Corporate | H45: Direct | I45: A. Patel | J45: Printers | K45: PRN-9787 | L45: 483.47 | M45: 1135.43 | N45: 0.146 | O45: 11
A46: ORD-2024-389336 | B46: 45432 | C46: 45445 | D46: Americas | E46: Canada | F46: Vancouver | G46: Enterprise | H46: Marketplace | I46: K. Singh | J46: Components | K46: CMP-5946 | L46: 675.43 | M46: 996.36 | N46: 0.182 | O46: 22
A47: ORD-2023-308124 | B47: 45035 | C47: 45046 | D47: Asia | E47: India | F47: Delhi | G47: Small Business | H47: Retail | I47: A. Patel | J47: Networking | K47: NET-2062 | L47: 826.55 | M47: 1397.05 | N47: 0.169 | O47: 28
... A77: ORD-2023-722117 | B77: 45187 | C77: 45207 | D77: Asia | E77: India | F77: Delhi | G77: Small Business | H77: Direct | I77: B. Chen | J77: Components | K77: CMP-1009 | L77: 825.64 | M77: 1108.43 | N77: 0.114 | O77: 7
A78: ORD-2024-446699 | B78: 45532 | C78: 45560 | D78: Americas | E78: Brazil | F78: Rio de Janeiro | G78: Non-Profit | H78: Online | J78: Accessories | K78: ACC-4490 | L78: 1394.65 | M78: 3144.1 | N78: 0.134 | O78: 13
A79: ORD-2024-451005 | B79: 45473 | C79: 45471 | D79: Americas | E79: Brazil | F79: Rio de Janeiro | G79: Small Business | H79: Direct | I79: L. Okafor | J79: Accessories | K79: ACC-9162 | L79: 1112.98 | M79: 2095.73 | N79: 0.072 | O79: 17
A80: ORD-2023-290279 | B80: 45091 | C80: 45093 | D80: Europe | E80: United Kingdom | F80: Manchester | G80: Non-Profit | H80: Direct | I80: K. Singh | J80: Components | K80: CMP-5820 | L80: 357.36 | M80: 703.62 | N80: 0.257 | O80: 20
A81: ORD-2024-192263 | B81: 45617 | C81: 45647 | D81: Europe | E81: France | F81: Marseille | G81: Small Business | H81: Direct | I81: I. Johnson | J81: Monitors | K81: MON-7943 | L81: 1122.68 | M81: 1997.19 | N81: 0.186 | O81: 3
A82: ORD-2023-159379 | B82: 44965 | C82: 44968 | D82: Africa | E82: South Africa | F82: Cape Town | G82: Corporate | H82: Direct | I82: M. Rossi | J82: Networking | K82: NET-5018 | L82: 1410.05 | M82: 2763.95 | N82: 0.161 | O82: 26
A83: ORD-2023-343322 | B83: 45157 | C83: 45181 | D83: Americas | E83: Canada | F83: Vancouver | G83: Enterprise | H83: Retail | I83: I. Johnson | J83: Printers | K83: PRN-9669 | L83: 1183.95 | M83: 1503.53 | N83: 0.241 | O83: 16
A84: ORD-2025-114382 | B84: 45791 | C84: 45801 | D84: Europe | E84: France | F84: Paris | G84: Small Business | H84: Marketplace | I84: K. Singh | J84: Components | K84: CMP-2865 | L84: 170.39 | M84: 388.04 | N84: 0.084 | O84: 15
A85: ORD-2025-488349 | B85: 45770 | C85: 45769 | D85: Americas | E85: USA | F85: San Francisco | G85: Non-Profit | H85: Distributor | I85: D. Smith | J85: Monitors | K85: MON-3371 | L85: 23.24 | M85: 44.57 | N85: 0.215 | O85: 15
A86: ORD-2025-330203 | B86: 45741 | C86: 45764 | D86: Europe | E86: United Kingdom | F86: London | G86: Consumer | H86: Retail | I86: H. Kim | J86: Networking | K86: NET-7166 | L86: 1421.19 | M86: 1808.26 | N86: 0.104 | O86: 13
A87: ORD-2023-841426 | B87: 45282 | C87: 45283 | D87: Africa | E87: South Africa | F87: Cape Town | G87: Non-Profit | H87: Marketplace | I87: D. Smith | J87: Components | K87: CMP-4531 | L87: 1186.18 | M87: 1285.09 | N87: 0.07 | O87: 11
A88: ORD-2024-594592 | B88: 45388 | C88: 45407 | D88: Asia | E88: China | F88: Shanghai | G88: Corporate | H88: Retail | I88: K. Singh | J88: Components | K88: CMP-8196 | L88: 1366.48 | M88: 1678.14 | N88: 0.154 | O88: 10
A89: ORD-2025-863978 | B89: 45876 | C89: 45888 | D89: Africa | E89: Kenya | F89: Nakuru | G89: Corporate | I89: M. Rossi | J89: Components | K89: CMP-2854 | L89: 601.51 | M89: 679.35 | N89: 0.188 | O89: 3
A90: ORD-2024-604471 | B90: 45312 | C90: 45316 | D90: Asia | E90: India | F90: Delhi | G90: Consumer | H90: Direct | I90: C. Otieno | J90: Monitors | K90: MON-8973 | L90: 523.7 | M90: 1109.92 | N90: 0.03 | O90: 11
A91: ORD-2023-258768 | B91: 45106 | C91: 45109 | D91: Asia | E91: Japan | F91: Nagoya | G91: Education | H91: Marketplace | I91: F. Müller | J91: Monitors | K91: MON-2990 | L91: 55.65 | M91: 83.57 | N91: 0.066 | O91: 8
A92: ORD-2025-626047 | B92: 45775 | C92: 45792 | D92: Asia | E92: Japan | F92: Nagoya | G92: Education | H92: Direct | I92: N. Brown | J92: Networking | K92: NET-1966 | L92: 691.19 | M92: 1284.3 | N92: 0.074 | O92: 7
A93: ORD-2025-526752 | B93: 45817 | C93: 45833 | D93: Asia | E93: India | F93: Hyderabad | G93: Enterprise | H93: Distributor | I93: M. Rossi | J93: Phones | K93: PHN-3482 | L93: 527.33 | M93: 911.72 | N93: 0.144 | O93: 25
A94: ORD-2023-374486 | B94: 45101 | C94: 45100 | D94: Americas | E94: Brazil | F94: Rio de Janeiro | G94: Non-Profit | H94: Retail | I94: E. Garcia | J94: Printers | K94: PRN-6490 | L94: 804.01 | M94: 1405.07 | N94: 0.096 | O94: 8
A95: ORD-2024-997336 | B95: 45569 | C95: 45598 | D95: Africa | E95: Nigeria | F95: Abuja | G95: Corporate | H95: Distributor | I95: F. Müller | J95: Accessories | K95: ACC-9038 | L95: 412.09 | M95: 968.94 | N95: 0.099 | O95: 23
A96: ORD-2025-725646 | B96: 45910 | C96: 45930 | D96: Africa | E96: Kenya | F96: Mombasa | G96: Corporate | H96: Direct | I96: L. Okafor | J96: Phones | K96: PHN-6954 | L96: 1009.48 | M96: 1088.81 | N96: 0.16 | O96: 6
A97: ORD-2023-868734 | B97: 45022 | C97: 45043 | D97: Europe | E97: United Kingdom | F97: Manchester | G97: Enterprise | H97: Distributor | I97: I. Johnson | J97: Printers | K97: PRN-8970 | L97: 1084.79 | M97: 2484.99 | N97: 0.034 | O97: 18
A98: ORD-2025-262491 | B98: 45870 | C98: 45885 | D98: Asia | E98: India | G98: Enterprise | H98: Direct | I98: O. Wang | J98: Monitors | K98: MON-1822 | L98: 24.44 | M98: 28.69 | N98: 0.146 | O98: 6
A99: ORD-2024-638884 | B99: 45440 | C99: 45438 | D99: Africa | E99: Nigeria | F99: Abuja | G99: Enterprise | H99: Online | I99: F. Müller | J99: Accessories | K99: ACC-5177 | L99: 1227.08 | M99: 1896.62 | N99: 0 | O99: 18
A100: ORD-2025-541501 | B100: 45860 | C100: 45887 | D100: Asia | E100: China | F100: Shenzhen | G100: Non-Profit | H100: Marketplace | I100: M. Rossi | J100: Networking | K100: NET-1804 | L100: 547.32 | M100: 419.17 | N100: 0.092 | O100: 14
A101: ORD-2023-422918 | B101: 44985 | C101: 45005 | D101: Europe | E101: Germany | F101: Berlin | G101: Small Business | H101: Direct | I101: H. Kim | J101: Laptops | K101: LAP-3679 | L101: 1200.78 | M101: 2001.17 | N101: 0.292 | O101: 18
A102: ORD-2025-328504 | B102: 45684 | C102: 45703 | D102: Asia | E102: China | F102: Shenzhen | G102: Non-Profit | H102: Direct | I102: L. Okafor | J102: Phones | K102: PHN-8368 | L102: 1253.22 | M102: 3104.71 | N102: 0 | O102: 17
A103: ORD-2024-851883 | B103: 45304 | C103: 45313 | D103: Asia | E103: India | F103: Mumbai | G103: Enterprise | H103: Marketplace | I103: J. Njeri | J103: Components | K103: CMP-8141 | L103: 313.6 | M103: 334.28 | N103: 0.14 | O103: 22
A104: ORD-2025-662997 | B104: 45747 | C104: 45751 | D104: Africa | E104: Kenya | F104: Nakuru | G104: Corporate | H104: Direct | I104: C. Otieno | J104: Laptops | K104: LAP-7136 | L104: 862.08 | M104: 1952.83 | N104: 0 | O104: 7
A105: ORD-2024-478165 | B105: 45631 | C105: 45654 | D105: Americas | E105: Canada | F105: Vancouver | G105: Corporate | H105: Direct | I105: F. Müller | J105: Accessories | K105: ACC-2386 | L105: 107.03 | M105: 242.29 | N105: 0.18 | O105: 30
A106: ORD-2024-771210 | B106: 45549 | C106: 45570 | D106: Asia | E106: China | F106: Shanghai | G106: Small Business | H106: Online | I106: H. Kim | J106: Laptops | K106: LAP-5150 | L106: 1405.56 | M106: 2968.87 | N106: 0.169 | O106: 5
A107: ORD-2024-155337 | B107: 45433 | C107: 45439 | D107: Africa | E107: South Africa | F107: Johannesburg | G107: Non-Profit | H107: Online | I107: M. Rossi | J107: Components | K107: CMP-8101 | L107: 1157.51 | M107: 1394.3 | N107: 0.278 | O107: 12
A108: ORD-2023-251563 | B108: 45057 | C108: 45084 | D108: Africa | E108: Kenya | F108: Mombasa | G108: Corporate | H108: Online | I108: J. Njeri | J108: Phones | K108: PHN-8970 | L108: 12.85 | M108: 15.41 | N108: 0.137 | O108: 39
A109: ORD-2024-286833 | B109: 45518 | C109: 45539 | D109: Europe | E109: United Kingdom | F109: Manchester | G109: Non-Profit | H109: Online | I109: J. Njeri | J109: Phones | K109: PHN-2341 | L109: 1138.8 | M109: 2250.81 | N109: 0.123 | O109: 12
A110: ORD-2024-792558 | B110: 45581 | C110: 45604 | D110: Asia | E110: Japan | F110: Osaka | G110: Small Business | H110: Retail | I110: J. Njeri | J110: Networking | K110: NET-6387 | L110: 82.14 | M110: 166.04 | N110: 0 | O110: 10
... A121: ORD-2025-956101 | B121: 45847 | C121: 45856 | D121: Americas | E121: Canada | F121: Vancouver | G121: Education | H121: Distributor | I121: I. Johnson | J121: Laptops | K121: LAP-2218 | L121: 57.96 | M121: 88.51 | N121: 0.043 | O121: 7
A122: ORD-2025-184082 | B122: 45827 | C122: 45850 | D122: Europe | E122: United Kingdom | G122: Non-Profit | H122: Direct | J122: Networking | K122: NET-6370 | L122: 801.24 | M122: 1959.09 | N122: 0.123 | O122: 23
A123: ORD-2023-576840 | B123: 45249 | C123: 45273 | D123: Europe | E123: France | F123: Lyon | G123: Non-Profit | H123: Direct | I123: H. Kim | J123: Monitors | K123: MON-3745 | L123: 1297.42 | M123: 2742.97 | N123: 0.069 | O123: 9
A124: ORD-2023-178249 | B124: 45289 | C124: 45311 | D124: Africa | E124: Kenya | F124: Kisumu | G124: Corporate | H124: Direct | I124: L. Okafor | J124: Phones | K124: PHN-7924 | L124: 1395.49 | M124: 1679.42 | N124: 0.203 | O124: 12
A125: ORD-2024-588972 | B125: 45598 | C125: 45625 | D125: Americas | E125: Brazil | F125: Brasília | G125: Small Business | H125: Direct | I125: I. Johnson | J125: Networking | K125: NET-8561 | L125: 1363.51 | M125: 1433.9 | N125: 0.057 | O125: 8
A126: ORD-2023-603238 | B126: 45159 | C126: 45173 | D126: Americas | E126: Canada | F126: Montreal | G126: Education | H126: Distributor | I126: F. Müller | J126: Components | K126: CMP-2136 | L126: 178.19 | M126: 284.43 | N126: 0.089 | O126: 8
A127: ORD-2023-883066 | B127: 45150 | C127: 45175 | D127: Asia | E127: China | F127: Shanghai | G127: Small Business | H127: Retail | I127: B. Chen | J127: Components | K127: CMP-6352 | L127: 950.77 | M127: 694.78 | N127: 0.084 | O127: 14
A128: ORD-2024-584090 | B128: 45450 | C128: 45469 | D128: Europe | E128: Germany | F128: Berlin | G128: Non-Profit | H128: Marketplace | I128: M. Rossi | J128: Components | K128: CMP-2040 | L128: 1064.32 | M128: 1848.39 | N128: 0.073 | O128: 38
A129: ORD-2025-537785 | B129: 45874 | C129: 45883 | D129: Europe | E129: United Kingdom | F129: London | G129: Non-Profit | H129: Direct | I129: E. Garcia | J129: Components | K129: CMP-6346 | L129: 41.76 | M129: 45.19 | N129: 0.179 | O129: 23
A130: ORD-2024-605518 | B130: 45442 | C130: 45456 | D130: Americas | E130: USA | F130: San Francisco | G130: Small Business | H130: Retail | I130: F. Müller | J130: Phones | K130: PHN-4356 | L130: 157.78 | M130: 361.1 | N130: 0.187 | O130: 9
A131: ORD-2023-521818 | B131: 44948 | C131: 44956 | D131: Americas | E131: USA | F131: San Francisco | G131: Small Business | H131: Online | I131: A. Patel | J131: Networking | K131: NET-4155 | L131: 413.52 | M131: 1004.34 | N131: 0.111 | O131: 18
A132: ORD-2025-650719 | B132: 45700 | C132: 45716 | D132: Americas | E132: Brazil | F132: São Paulo | G132: Non-Profit | H132: Direct | I132: B. Chen | J132: Monitors | K132: MON-5179 | L132: 414.95 | M132: 1027.73 | N132: 0.063 | O132: 8
A133: ORD-2025-501927 | B133: 45719 | C133: 45740 | D133: Africa | E133: Nigeria | F133: Abuja | G133: Enterprise | H133: Direct | I133: H. Kim | J133: Accessories | K133: ACC-4056 | L133: 555.95 | M133: 468.09 | N133: 0.142 | O133: 11
A134: ORD-2023-430904 | B134: 44953 | C134: 44957 | D134: Europe | E134: United Kingdom | F134: Manchester | G134: Enterprise | H134: Online | I134: N. Brown | J134: Laptops | K134: LAP-9782 | L134: 941.2 | M134: 668.02 | N134: 0.22 | O134: 16
... A187: ORD-2023-399631 | B187: 45099 | C187: 45128 | D187: Europe | E187: France | F187: Lyon | G187: Corporate | H187: Retail | I187: J. Njeri | J187: Accessories | K187: ACC-3385 | L187: 734.34 | M187: 887.9 | N187: 0.025 | O187: 12
A188: ORD-2025-542939 | B188: 45670 | C188: 45696 | D188: Europe | E188: France | F188: Paris | G188: Non-Profit | I188: E. Garcia | J188: Monitors | K188: MON-1593 | L188: 594.74 | M188: 1020.69 | N188: 0.211 | O188: 6
A189: ORD-2023-521818 | B189: 44955 | C189: 44985 | D189: Asia | E189: India | F189: Bengaluru | G189: Non-Profit | H189: Retail | I189: B. Chen | J189: Accessories | K189: ACC-4631 | L189: 1262.1 | M189: 1395.53 | N189: 0.233 | O189: 25
A190: ORD-2023-825836 | B190: 45126 | C190: 45138 | D190: Americas | E190: Brazil | F190: Rio de Janeiro | G190: Corporate | H190: Retail | I190: C. Otieno | J190: Monitors | K190: MON-7869 | L190: 1334.64 | M190: 2273.42 | N190: 0.118 | O190: 14
A191: ORD-2024-503082 | B191: 45431 | C191: 45451 | D191: Americas | E191: Brazil | F191: Brasília | G191: Small Business | H191: Retail | I191: E. Garcia | J191: Monitors | K191: MON-4271 | L191: 1075.9 | M191: 1242.15 | N191: 0.012 | O191: 7
A192: ORD-2024-760799 | B192: 45325 | C192: 45341 | D192: Asia | E192: China | F192: Shenzhen | G192: Small Business | H192: Online | I192: H. Kim | J192: Laptops | K192: LAP-5531 | L192: 993.75 | M192: 1310.29 | N192: 0.215 | O192: 19
A193: ORD-2023-197661 | B193: 45146 | C193: 45160 | D193: Europe | E193: United Kingdom | F193: Birmingham | G193: Non-Profit | H193: Direct | I193: N. Brown | J193: Monitors | K193: MON-7511 | L193: 446.69 | M193: 967.25 | N193: 0.094 | O193: 10
A194: ORD-2024-212990 | B194: 45516 | C194: 45538 | D194: Americas | E194: USA | F194: Austin | G194: Consumer | H194: Distributor | I194: I. Johnson | J194: Laptops | K194: LAP-7979 | L194: 797.8 | M194: 886.22 | N194: 0.236 | O194: 36
A195: ORD-2023-925146 | B195: 45214 | C195: 45243 | D195: Asia | E195: China | F195: Shenzhen | G195: Non-Profit | H195: Distributor | I195: J. Njeri | J195: Printers | K195: PRN-4983 | L195: 986.44 | M195: 790.61 | N195: 0.072 | O195: 6
A196: ORD-2023-177794 | B196: 45050 | C196: 45072 | D196: Americas | E196: USA | F196: San Francisco | G196: Enterprise | H196: Online | I196: J. Njeri | J196: Networking | K196: NET-5941 | L196: 249.71 | M196: 361.33 | N196: 0.094 | O196: 12
A197: ORD-2024-444710 | B197: 45557 | C197: 45566 | D197: Americas | E197: Brazil | F197: São Paulo | G197: Non-Profit | H197: Online | I197: K. Singh | J197: Monitors | K197: MON-6341 | L197: 1378.8 | M197: 1952.04 | N197: 0.159 | O197: 19
A198: ORD-2024-668926 | B198: 45588 | C198: 45610 | D198: Asia | E198: Japan | F198: Osaka | G198: Non-Profit | H198: Direct | I198: B. Chen | J198: Phones | K198: PHN-9789 | L198: 1406.4 | M198: 1564.76 | N198: 0.185 | O198: 17
A199: ORD-2024-968374 | B199: 45333 | C199: 45354 | D199: Africa | E199: Kenya | F199: Kisumu | G199: Enterprise | H199: Online | I199: B. Chen | J199: Phones | K199: PHN-5082 | L199: 516.86 | M199: 852.54 | N199: 0.051 | O199: 14
A200: ORD-2023-575584 | B200: 44956 | C200: 44978 | D200: Europe | E200: Germany | F200: Munich | G200: Small Business | H200: Marketplace | I200: G. Dubois | J200: Networking | K200: NET-3460 | L200: 1142.88 | M200: 1465.29 | N200: 0.186 | O200: 7
... A236: ORD-2023-946143 | B236: 44999 | C236: 45015 | D236: Africa | E236: South Africa | F236: Cape Town | G236: Consumer | H236: Distributor | I236: K. Singh | J236: Components | K236: CMP-8230 | L236: 1309.77 | M236: 1589.07 | N236: 0.102 | O236: 10
A237: ORD-2024-281211 | B237: 45302 | C237: 45324 | D237: Asia | E237: Japan | F237: Nagoya | G237: Small Business | H237: Online | J237: Printers | K237: PRN-7816 | L237: 1237.68 | M237: 1432.8 | N237: 0.068 | O237: 13
A238: ORD-2024-805860 | B238: 45548 | C238: 45567 | D238: Africa | E238: Kenya | F238: Mombasa | G238: Small Business | H238: Retail | I238: M. Rossi | J238: Phones | K238: PHN-8804 | L238: 1338.99 | M238: 1765.76 | N238: 0.126 | O238: 24
A239: ORD-2025-132174 | B239: 45855 | C239: 45861 | D239: Americas | E239: Canada | F239: Vancouver | G239: Consumer | H239: Online | I239: H. Kim | J239: Components | K239: CMP-8851 | L239: 1364.89 | M239: 2757.54 | N239: 0.172 | O239: 61
A240: ORD-2023-964434 | B240: 45258 | C240: 45267 | D240: Asia | E240: India | F240: Delhi | G240: Enterprise | H240: Marketplace | I240: L. Okafor | J240: Phones | K240: PHN-2447 | L240: 699.33 | M240: 873.75 | N240: 0.235 | O240: 10
A241: ORD-2024-897622 | B241: 45381 | C241: 45406 | D241: Americas | E241: USA | F241: Austin | G241: Non-Profit | H241: Online | I241: G. Dubois | J241: Laptops | K241: LAP-2846 | L241: 160.82 | M241: 258.52 | N241: 0.13 | O241: 17
A242: ORD-2023-517216 | B242: 45188 | C242: 45207 | D242: Asia | E242: India | F242: Bengaluru | G242: Education | H242: Direct | I242: J. Njeri | J242: Printers | K242: PRN-5005 | L242: 385.32 | M242: 606.76 | N242: 0.086 | O242: 8
A243: ORD-2025-509940 | B243: 45793 | C243: 45804 | D243: Asia | E243: China | F243: Beijing | G243: Enterprise | H243: Online | I243: F. Müller | J243: Phones | K243: PHN-3800 | L243: 918.12 | M243: 1337.69 | N243: 0.095 | O243: 8
A244: ORD-2025-646342 | B244: 45871 | C244: 45877 | D244: Asia | E244: Japan | F244: Osaka | G244: Consumer | H244: Direct | I244: N. Brown | J244: Laptops | K244: LAP-4828 | L244: 1225.94 | M244: 1793.08 | N244: 0.136 | O244: 22
A245: ORD-2024-866535 | B245: 45630 | C245: 45638 | D245: Europe | E245: Germany | F245: Frankfurt | G245: Enterprise | H245: Marketplace | I245: B. Chen | J245: Printers | K245: PRN-5492 | L245: 72.06 | M245: 122.74 | N245: 0.238 | O245: 8
A246: ORD-2023-747341 | B246: 45035 | C246: 45044 | D246: Americas | E246: Brazil | F246: Rio de Janeiro | G246: Corporate | H246: Distributor | I246: M. Rossi | J246: Phones | K246: PHN-7132 | L246: 1013.54 | M246: 927.93 | N246: 0.175 | O246: 16
...

Sheet ReadMe
A1: Sales Operations & Analytics
A4: 1. DATA ISSUES FOUND (in original_data, 632 rows)
A5: • Missing values: 8 blank City, 8 blank Channel, 8 blank Salesperson.
A6: • RequiredDate earlier than OrderDate on some rows (negative lead time).
A7: • Discounts above the 30% policy cap (flagged); largest observed 56.5%.
A8: • Cost > Price on some lines, producing negative gross profit.
A9: • Mixed/unstandardised dimensions requiring Month / Quarter / Price-band derivation.
A11: 2. CLEANING RULES APPLIED (see clean_data / Table1)
A12: • Duplicates: rows treated as unique by OrderID; no exact full-row duplicates were found, so none removed.
A13: • Data types: OrderDate / RequiredDate stored as dates; cost, price, qty, discount as numbers.
A14: • Missing City -> imputed with the most common City for that Country (mode).
A15: • Missing Channel -> imputed with the most common Channel for that Country (mode).
... A47: • No hard-coded totals: every measure is a live Excel formula or PivotTable.

Sheet Brief
A1: Assignment
A2: Excel Mastery Assignment: Sales Operations & Analytics
A4: Overview:
A5: You are an analyst for a multi-regional electronics distributor. The 'Data' sheet contains 632 rows and 15 columns of transactional data with intentional data-quality issues.
A6: Your job is to clean, enrich, analyze, and present insights via a dynamic dashboard.
A8: Part A — Data Cleaning & Preparation:
A9: 1) Create a staging table where you:
A10: • Remove exact duplicate rows (define and document your duplicate criteria).
A11: • Fix data types (dates as Dates, numeric fields as numbers).
A12: • Handle missing values for City, Salesperson, and Channel using reasonable business logic (document your approach).
A13: • Flag and correct suspicious UnitPrice values (e.g., negative prices) and discounts (e.g., > 30%).
A14: • Ensure RequiredDate is not earlier than OrderDate; where it is, impute a corrected RequiredDate (explain your rule).
... A67: 15) Ensure your dashboard responds to slicers without broken references.

Sheet clean_data
A1: OrderID | B1: short_order_id | C1: order_year | D1: first_time_orders | E1: Cohort | F1: OrderDate | G1: MMM-YYYY | H1: months | I1: quarters | J1: lead_time | K1: adj_lead_time | L1: lead_proxy | M1: RequiredDate | N1: adj_required_date | O1: Region | P1: Country | Q1: City | R1: CustomerSegment | S1: Channel | T1: Salesperson | U1: ProductCategory | V1: SKU | W1: UnitCost | X1: adj_unit_cost | Y1: UnitPrice | Z1: price_band | AA1: DiscountPct | AB1: cap_adjusted_discount | AC1: discount>30% | AD1: Quantity | AE1: scenario_quantity | AF1: cost_of_goods | AG1: Category_revenue | AH1: Cumulative_revenue | AI1: cumulative_pct | AJ1: ABC | AK1: Scenario_unit_cost | AL1: scenario_revenue | AM1: gross_revenue | AN1: gross_profit | AO1: scenario_profit | AP1: Margin %
A2: ORD-2023-960380 | B2: =_xlfn.TEXTAFTER(Table1[[#This Row],[OrderID]],"-",2) -> 960380 | C2: =YEAR(Table1[[#This Row],[OrderDate]]) -> 2023 | D2: =_xlfn.MINIFS(F:F,P:P,Table1[[#This Row],[Country]]) -> 44941 | E2: =DATEDIF(Table1[[#This Row],[first_time_orders]],Table1[[#This Row],[OrderDate]],"m") -> 0 | F2: 44968 | G2: =TEXT(Table1[[#This Row],[OrderDate]],"MMM-YYYY") -> Feb-2023 | H2: =MONTH(Table1[[#This Row],[OrderDate]]) -> 2 | I2: ="Q"&ROUNDUP(Table1[[#This Row],[months]]/3,0)&"-"&Table1[[#This Row],[order_year]] -> Q1-2023 | J2: =Table1[[#This Row],[RequiredDate]]-Table1[[#This Row],[OrderDate]] -> 1 | K2: =IF(Table1[[#This Row],[lead_time]]<0,MEDIAN(J:J),Table1[[#This Row],[lead_time]]) -> 1 | L2: =IF(Table1[[#This Row],[adj_lead_time]]<=7,1,0) -> 1 | M2: 44969 | N2: =IF(Table1[[#This Row],[lead_time]]<0,(Table1[[#This Row],[OrderDate]]+Table1[[#This Row],[adj_lead_time]]),Table1[[#This Row],[RequiredDate]]) -> 44969 | O2: Africa | P2: Nigeria | Q2: Port Harcourt | R2: Non-Profit | S2: Direct | T2: D. Smith | U2: Accessories | V2: ACC-8242 | W2: 944.61 | X2: =Table1[[#This Row],[UnitCost]]*(1+'scenario modeling'!$B$3) -> 1039.071 | Y2: 839.04 | Z2: =IF(Table1[[#This Row],[UnitPrice]]<=Quantiles!$B$2,Quantiles!$A$2,IF(Table1[[#This Row],[UnitPrice]]<=Quantiles!$B$3,Quantiles!$A$3,Quantiles!$A$4)) -> Medium | AA2: 0.059 | AB2: =MIN(Table1[[#This Row],[DiscountPct]],'scenario modeling'!$B$2) -> 0.059 | AC2: =IF(Table1[[#This Row],[DiscountPct]]>0.3, ">0.3","") | AD2: 6 | AE2: =Table1[[#This Row],[Quantity]]*(1+'scenario modeling'!$B$4) -> 7.2 | AF2: =Table1[[#This Row],[UnitCost]]*Table1[[#This Row],[Quantity]] -> 5667.66 | AG2: =SUMIF($U:U,Table1[[#This Row],[ProductCategory]],$AM:AM) -> 1331102.9 | AH2: =SUMIFS($AM$2:AM2,$U$2:U2,U2) -> 4737.2198 | AI2: =Table1[[#This Row],[Cumulative_revenue]]/Table1[[#This Row],[Category_revenue]] -> 0.0035588681 | AJ2: =IF(Table1[[#This Row],[cumulative_pct]]<=0.8,"A",IF(Table1[[#This Row],[cumulative_pct]]<=0.95,"B","C")) -> A | AK2: =Table1[[#This Row],[adj_unit_cost]]*Table1[[#This Row],[scenario_quantity]] -> 7481.3112 | AL2: =Table1[[#This Row],[UnitPrice]]*Table1[[#This Row],[scenario_quantity]]*(1-Table1[[#This Row],[cap_adjusted_discount]]) -> 5684.6638 | AM2: =Table1[[#This Row],[UnitPrice]]*Table1[[#This Row],[Quantity]]*(1-Table1[[#This Row],[DiscountPct]]) -> 4737.2198 | AN2: =Table1[[#This Row],[gross_revenue]]-Table1[[#This Row],[cost_of_goods]] -> -930.44016 | AO2: =Table1[[#This Row],[scenario_revenue]]-Table1[[#This Row],[Scenario_unit_cost]] -> -1796.6474 | AP2: =IF(Table1[[#This Row],[gross_revenue]]=0,0,Table1[[#This Row],[gross_profit]]/Table1[[#This Row],[gross_revenue]]) -> -0.19641059
A3: ORD-2023-521818 | B3: =_xlfn.TEXTAFTER(Table1[[#This Row],[OrderID]],"-",2) -> 521818 | C3: =YEAR(Table1[[#This Row],[OrderDate]]) -> 2023 | D3: =_xlfn.MINIFS(F:F,P:P,Table1[[#This Row],[Country]]) -> 44955 | E3: =DATEDIF(Table1[[#This Row],[first_time_orders]],Table1[[#This Row],[OrderDate]],"m") -> 0 | F3: 44955 | G3: =TEXT(Table1[[#This Row],[OrderDate]],"MMM-YYYY") -> Jan-2023 | H3: =MONTH(Table1[[#This Row],[OrderDate]]) -> 1 | I3: ="Q"&ROUNDUP(Table1[[#This Row],[months]]/3,0)&"-"&Table1[[#This Row],[order_year]] -> Q1-2023 | J3: =Table1[[#This Row],[RequiredDate]]-Table1[[#This Row],[OrderDate]] -> 30 | K3: =IF(Table1[[#This Row],[lead_time]]<0,MEDIAN(J:J),Table1[[#This Row],[lead_time]]) -> 30 | L3: =IF(Table1[[#This Row],[adj_lead_time]]<=7,1,0) -> 0 | M3: 44985 | N3: =IF(Table1[[#This Row],[lead_time]]<0,(Table1[[#This Row],[OrderDate]]+Table1[[#This Row],[adj_lead_time]]),Table1[[#This Row],[RequiredDate]]) -> 44985 | O3: Asia | P3: India | Q3: Bengaluru | R3: Non-Profit | S3: Retail | T3: B. Chen | U3: Accessories | V3: ACC-4631 | W3: 1262.1 | X3: =Table1[[#This Row],[UnitCost]]*(1+'scenario modeling'!$B$3) -> 1388.31 | Y3: 1395.53 | Z3: =IF(Table1[[#This Row],[UnitPrice]]<=Quantiles!$B$2,Quantiles!$A$2,IF(Table1[[#This Row],[UnitPrice]]<=Quantiles!$B$3,Quantiles!$A$3,Quantiles!$A$4)) -> Medium | AA3: 0.233 | AB3: =MIN(Table1[[#This Row],[DiscountPct]],'scenario modeling'!$B$2) -> 0.1 | AC3: =IF(Table1[[#This Row],[DiscountPct]]>0.3, ">0.3","") | AD3: 25 | AE3: =Table1[[#This Row],[Quantity]]*(1+'scenario modeling'!$B$4) -> 30 | AF3: =Table1[[#This Row],[UnitCost]]*Table1[[#This Row],[Quantity]] -> 31552.5 | AG3: =SUMIF($U:U,Table1[[#This Row],[ProductCategory]],$AM:AM) -> 1331102.9 | AH3: =SUMIFS($AM$2:AM3,$U$2:U3,U3) -> 31496.508 | AI3: =Table1[[#This Row],[Cumulative_revenue]]/Table1[[#This Row],[Category_revenue]] -> 0.023661962 | AJ3: =IF(Table1[[#This Row],[cumulative_pct]]<=0.8,"A",IF(Table1[[#This Row],[cumulative_pct]]<=0.95,"B","C")) -> A | AK3: =Table1[[#This Row],[adj_unit_cost]]*Table1[[#This Row],[scenario_quantity]] -> 41649.3 | AL3: =Table1[[#This Row],[UnitPrice]]*Table1[[#This Row],[scenario_quantity]]*(1-Table1[[#This Row],[cap_adjusted_discount]]) -> 37679.31 | AM3: =Table1[[#This Row],[UnitPrice]]*Table1[[#This Row],[Quantity]]*(1-Table1[[#This Row],[DiscountPct]]) -> 26759.288 | AN3: =Table1[[#This Row],[gross_revenue]]-Table1[[#This Row],[cost_of_goods]] -> -4793.2122 | AO3: =Table1[[#This Row],[scenario_revenue]]-Table1[[#This Row],[Scenario_unit_cost]] -> -3969.99 | AP3: =IF(Table1[[#This Row],[gross_revenue]]=0,0,Table1[[#This Row],[gross_profit]]/Table1[[#This Row],[gross_revenue]]) -> -0.17912331
A4: ORD-2023-780206 | B4: =_xlfn.TEXTAFTER(Table1[[#This Row],[OrderID]],"-",2) -> 780206 | C4: =YEAR(Table1[[#This Row],[OrderDate]]) -> 2023 | D4: =_xlfn.MINIFS(F:F,P:P,Table1[[#This Row],[Country]]) -> 44945 | E4: =DATEDIF(Table1[[#This Row],[first_time_orders]],Table1[[#This Row],[OrderDate]],"m") -> 0 | F4: 44945 | G4: =TEXT(Table1[[#This Row],[OrderDate]],"MMM-YYYY") -> Jan-2023 | H4: =MONTH(Table1[[#This Row],[OrderDate]]) -> 1 | I4: ="Q"&ROUNDUP(Table1[[#This Row],[months]]/3,0)&"-"&Table1[[#This Row],[order_year]] -> Q1-2023 | J4: =Table1[[#This Row],[RequiredDate]]-Table1[[#This Row],[OrderDate]] -> 15 | K4: =IF(Table1[[#This Row],[lead_time]]<0,MEDIAN(J:J),Table1[[#This Row],[lead_time]]) -> 15 | L4: =IF(Table1[[#This Row],[adj_lead_time]]<=7,1,0) -> 0 | M4: 44960 | N4: =IF(Table1[[#This Row],[lead_time]]<0,(Table1[[#This Row],[OrderDate]]+Table1[[#This Row],[adj_lead_time]]),Table1[[#This Row],[RequiredDate]]) -> 44960 | O4: Europe | P4: United Kingdom | Q4: London | R4: Enterprise | S4: Distributor | T4: G. Dubois | U4: Accessories | V4: ACC-3645 | W4: 873.06 | X4: =Table1[[#This Row],[UnitCost]]*(1+'scenario modeling'!$B$3) -> 960.366 | Y4: 2101.55 | Z4: =IF(Table1[[#This Row],[UnitPrice]]<=Quantiles!$B$2,Quantiles!$A$2,IF(Table1[[#This Row],[UnitPrice]]<=Quantiles!$B$3,Quantiles!$A$3,Quantiles!$A$4)) -> High | AA4: 0.066 | AB4: =MIN(Table1[[#This Row],[DiscountPct]],'scenario modeling'!$B$2) -> 0.066 | AC4: =IF(Table1[[#This Row],[DiscountPct]]>0.3, ">0.3","") | AD4: 10 | AE4: =Table1[[#This Row],[Quantity]]*(1+'scenario modeling'!$B$4) -> 12 | AF4: =Table1[[#This Row],[UnitCost]]*Table1[[#This Row],[Quantity]] -> 8730.6 | AG4: =SUMIF($U:U,Table1[[#This Row],[ProductCategory]],$AM:AM) -> 1331102.9 | AH4: =SUMIFS($AM$2:AM4,$U$2:U4,U4) -> 51124.985 | AI4: =Table1[[#This Row],[Cumulative_revenue]]/Table1[[#This Row],[Category_revenue]] -> 0.038407987 | AJ4: =IF(Table1[[#This Row],[cumulative_pct]]<=0.8,"A",IF(Table1[[#This Row],[cumulative_pct]]<=0.95,"B","C")) -> A | AK4: =Table1[[#This Row],[adj_unit_cost]]*Table1[[#This Row],[scenario_quantity]] -> 11524.392 | AL4: =Table1[[#This Row],[UnitPrice]]*Table1[[#This Row],[scenario_quantity]]*(1-Table1[[#This Row],[cap_adjusted_discount]]) -> 23554.172 | AM4: =Table1[[#This Row],[UnitPrice]]*Table1[[#This Row],[Quantity]]*(1-Table1[[#This Row],[DiscountPct]]) -> 19628.477 | AN4: =Table1[[#This Row],[gross_revenue]]-Table1[[#This Row],[cost_of_goods]] -> 10897.877 | AO4: =Table1[[#This Row],[scenario_revenue]]-Table1[[#This Row],[Scenario_unit_cost]] -> 12029.78 | AP4: =IF(Table1[[#This Row],[gross_revenue]]=0,0,Table1[[#This Row],[gross_profit]]/Table1[[#This Row],[gross_revenue]]) -> 0.55520747
A5: ORD-2023-107265 | B5: =_xlfn.TEXTAFTER(Table1[[#This Row],[OrderID]],"-",2) -> 107265 | C5: =YEAR(Table1[[#This Row],[OrderDate]]) -> 2023 | D5: =_xlfn.MINIFS(F:F,P:P,Table1[[#This Row],[Country]]) -> 44988 | E5: =DATEDIF(Table1[[#This Row],[first_time_orders]],Table1[[#This Row],[OrderDate]],"m") -> 1 | F5: 45038 | G5: =TEXT(Table1[[#This Row],[OrderDate]],"MMM-YYYY") -> Apr-2023 | H5: =MONTH(Table1[[#This Row],[OrderDate]]) -> 4 | I5: ="Q"&ROUNDUP(Table1[[#This Row],[months]]/3,0)&"-"&Table1[[#This Row],[order_year]] -> Q2-2023 | J5: =Table1[[#This Row],[RequiredDate]]-Table1[[#This Row],[OrderDate]] -> 22 | K5: =IF(Table1[[#This Row],[lead_time]]<0,MEDIAN(J:J),Table1[[#This Row],[lead_time]]) -> 22 | L5: =IF(Table1[[#This Row],[adj_lead_time]]<=7,1,0) -> 0 | M5: 45060 | N5: =IF(Table1[[#This Row],[lead_time]]<0,(Table1[[#This Row],[OrderDate]]+Table1[[#This Row],[adj_lead_time]]),Table1[[#This Row],[RequiredDate]]) -> 45060 | O5: Asia | P5: Japan | Q5: Nagoya | R5: Enterprise | S5: Retail | T5: A. Patel | U5: Accessories | V5: ACC-7713 | W5: 1209.22 | X5: =Table1[[#This Row],[UnitCost]]*(1+'scenario modeling'!$B$3) -> 1330.142 | Y5: 1404.33 | Z5: =IF(Table1[[#This Row],[UnitPrice]]<=Quantiles!$B$2,Quantiles!$A$2,IF(Table1[[#This Row],[UnitPrice]]<=Quantiles!$B$3,Quantiles!$A$3,Quantiles!$A$4)) -> Medium | AA5: 0.103 | AB5: =MIN(Table1[[#This Row],[DiscountPct]],'scenario modeling'!$B$2) -> 0.1 | AC5: =IF(Table1[[#This Row],[DiscountPct]]>0.3, ">0.3","") | AD5: 11 | AE5: =Table1[[#This Row],[Quantity]]*(1+'scenario modeling'!$B$4) -> 13.2 | AF5: =Table1[[#This Row],[UnitCost]]*Table1[[#This Row],[Quantity]] -> 13301.42 | AG5: =SUMIF($U:U,Table1[[#This Row],[ProductCategory]],$AM:AM) -> 1331102.9 | AH5: =SUMIFS($AM$2:AM5,$U$2:U5,U5) -> 64981.509 | AI5: =Table1[[#This Row],[Cumulative_revenue]]/Table1[[#This Row],[Category_revenue]] -> 0.048817794 | AJ5: =IF(Table1[[#This Row],[cumulative_pct]]<=0.8,"A",IF(Table1[[#This Row],[cumulative_pct]]<=0.95,"B","C")) -> A | AK5: =Table1[[#This Row],[adj_unit_cost]]*Table1[[#This Row],[scenario_quantity]] -> 17557.874 | AL5: =Table1[[#This Row],[UnitPrice]]*Table1[[#This Row],[scenario_quantity]]*(1-Table1[[#This Row],[cap_adjusted_discount]]) -> 16683.44 | AM5: =Table1[[#This Row],[UnitPrice]]*Table1[[#This Row],[Quantity]]*(1-Table1[[#This Row],[DiscountPct]]) -> 13856.524 | AN5: =Table1[[#This Row],[gross_revenue]]-Table1[[#This Row],[cost_of_goods]] -> 555.10411 | AO5: =Table1[[#This Row],[scenario_revenue]]-Table1[[#This Row],[Scenario_unit_cost]] -> -874.434 | AP5: =IF(Table1[[#This Row],[gross_revenue]]=0,0,Table1[[#This Row],[gross_profit]]/Table1[[#This Row],[gross_revenue]]) -> 0.040060848
A6: ORD-2023-674887 | B6: =_xlfn.TEXTAFTER(Table1[[#This Row],[OrderID]],"-",2) -> 674887 | C6: =YEAR(Table1[[#This Row],[OrderDate]]) -> 2023 | D6: =_xlfn.MINIFS(F:F,P:P,Table1[[#This Row],[Country]]) -> 44938 | E6: =DATEDIF(Table1[[#This Row],[first_time_orders]],Table1[[#This Row],[OrderDate]],"m") -> 11 | F6: 45276 | G6: =TEXT(Table1[[#This Row],[OrderDate]],"MMM-YYYY") -> Dec-2023 | H6: =MONTH(Table1[[#This Row],[OrderDate]]) -> 12 | I6: ="Q"&ROUNDUP(Table1[[#This Row],[months]]/3,0)&"-"&Table1[[#This Row],[order_year]] -> Q4-2023 | J6: =Table1[[#This Row],[RequiredDate]]-Table1[[#This Row],[OrderDate]] -> 3 | K6: =IF(Table1[[#This Row],[lead_time]]<0,MEDIAN(J:J),Table1[[#This Row],[lead_time]]) -> 3 | L6: =IF(Table1[[#This Row],[adj_lead_time]]<=7,1,0) -> 1 | M6: 45279 | N6: =IF(Table1[[#This Row],[lead_time]]<0,(Table1[[#This Row],[OrderDate]]+Table1[[#This Row],[adj_lead_time]]),Table1[[#This Row],[RequiredDate]]) -> 45279 | O6: Asia | P6: China | Q6: Beijing | R6: Education | S6: Retail | T6: A. Patel | U6: Accessories | V6: ACC-9644 | W6: 1415.05 | X6: =Table1[[#This Row],[UnitCost]]*(1+'scenario modeling'!$B$3) -> 1556.555 | Y6: 1972.38 | Z6: =IF(Table1[[#This Row],[UnitPrice]]<=Quantiles!$B$2,Quantiles!$A$2,IF(Table1[[#This Row],[UnitPrice]]<=Quantiles!$B$3,Quantiles!$A$3,Quantiles!$A$4)) -> High | AA6: 0 | AB6: =MIN(Table1[[#This Row],[DiscountPct]],'scenario modeling'!$B$2) -> 0 | AC6: =IF(Table1[[#This Row],[DiscountPct]]>0.3, ">0.3","") | AD6: 12 | AE6: =Table1[[#This Row],[Quantity]]*(1+'scenario modeling'!$B$4) -> 14.4 | AF6: =Table1[[#This Row],[UnitCost]]*Table1[[#This Row],[Quantity]] -> 16980.6 | AG6: =SUMIF($U:U,Table1[[#This Row],[ProductCategory]],$AM:AM) -> 1331102.9 | AH6: =SUMIFS($AM$2:AM6,$U$2:U6,U6) -> 88650.069 | AI6: =Table1[[#This Row],[Cumulative_revenue]]/Table1[[#This Row],[Category_revenue]] -> 0.066598958 | AJ6: =IF(Table1[[#This Row],[cumulative_pct]]<=0.8,"A",IF(Table1[[#This Row],[cumulative_pct]]<=0.95,"B","C")) -> A | AK6: =Table1[[#This Row],[adj_unit_cost]]*Table1[[#This Row],[scenario_quantity]] -> 22414.392 | AL6: =Table1[[#This Row],[UnitPrice]]*Table1[[#This Row],[scenario_quantity]]*(1-Table1[[#This Row],[cap_adjusted_discount]]) -> 28402.272 | AM6: =Table1[[#This Row],[UnitPrice]]*Table1[[#This Row],[Quantity]]*(1-Table1[[#This Row],[DiscountPct]]) -> 23668.56 | AN6: =Table1[[#This Row],[gross_revenue]]-Table1[[#This Row],[cost_of_goods]] -> 6687.96 | AO6: =Table1[[#This Row],[scenario_revenue]]-Table1[[#This Row],[Scenario_unit_cost]] -> 5987.88 | AP6: =IF(Table1[[#This Row],[gross_revenue]]=0,0,Table1[[#This Row],[gross_profit]]/Table1[[#This Row],[gross_revenue]]) -> 0.28256725
A7: ORD-2023-808024 | B7: =_xlfn.TEXTAFTER(Table1[[#This Row],[OrderID]],"-",2) -> 808024 | C7: =YEAR(Table1[[#This Row],[OrderDate]]) -> 2023 | D7: =_xlfn.MINIFS(F:F,P:P,Table1[[#This Row],[Country]]) -> 44936 | E7: =DATEDIF(Table1[[#This Row],[first_time_orders]],Table1[[#This Row],[OrderDate]],"m") -> 11 | F7: 45290 | G7: =TEXT(Table1[[#This Row],[OrderDate]],"MMM-YYYY") -> Dec-2023 | H7: =MONTH(Table1[[#This Row],[OrderDate]]) -> 12 | I7: ="Q"&ROUNDUP(Table1[[#This Row],[months]]/3,0)&"-"&Table1[[#This Row],[order_year]] -> Q4-2023 | J7: =Table1[[#This Row],[RequiredDate]]-Table1[[#This Row],[OrderDate]] -> 9 | K7: =IF(Table1[[#This Row],[lead_time]]<0,MEDIAN(J:J),Table1[[#This Row],[lead_time]]) -> 9 | L7: =IF(Table1[[#This Row],[adj_lead_time]]<=7,1,0) -> 0 | M7: 45299 | N7: =IF(Table1[[#This Row],[lead_time]]<0,(Table1[[#This Row],[OrderDate]]+Table1[[#This Row],[adj_lead_time]]),Table1[[#This Row],[RequiredDate]]) -> 45299 | O7: Europe | P7: France | Q7: Marseille | R7: Consumer | S7: Marketplace | T7: L. Okafor | U7: Accessories | V7: ACC-6594 | W7: 861.1 | X7: =Table1[[#This Row],[UnitCost]]*(1+'scenario modeling'!$B$3) -> 947.21 | Y7: 1224.72 | Z7: =IF(Table1[[#This Row],[UnitPrice]]<=Quantiles!$B$2,Quantiles!$A$2,IF(Table1[[#This Row],[UnitPrice]]<=Quantiles!$B$3,Quantiles!$A$3,Quantiles!$A$4)) -> Medium | AA7: 0.174 | AB7: =MIN(Table1[[#This Row],[DiscountPct]],'scenario modeling'!$B$2) -> 0.1 | AC7: =IF(Table1[[#This Row],[DiscountPct]]>0.3, ">0.3","") | AD7: 24 | AE7: =Table1[[#This Row],[Quantity]]*(1+'scenario modeling'!$B$4) -> 28.8 | AF7: =Table1[[#This Row],[UnitCost]]*Table1[[#This Row],[Quantity]] -> 20666.4 | AG7: =SUMIF($U:U,Table1[[#This Row],[ProductCategory]],$AM:AM) -> 1331102.9 | AH7: =SUMIFS($AM$2:AM7,$U$2:U7,U7) -> 112928.92 | AI7: =Table1[[#This Row],[Cumulative_revenue]]/Table1[[#This Row],[Category_revenue]] -> 0.084838606 | AJ7: =IF(Table1[[#This Row],[cumulative_pct]]<=0.8,"A",IF(Table1[[#This Row],[cumulative_pct]]<=0.95,"B","C")) -> A | AK7: =Table1[[#This Row],[adj_unit_cost]]*Table1[[#This Row],[scenario_quantity]] -> 27279.648 | AL7: =Table1[[#This Row],[UnitPrice]]*Table1[[#This Row],[scenario_quantity]]*(1-Table1[[#This Row],[cap_adjusted_discount]]) -> 31744.742 | AM7: =Table1[[#This Row],[UnitPrice]]*Table1[[#This Row],[Quantity]]*(1-Table1[[#This Row],[DiscountPct]]) -> 24278.849 | AN7: =Table1[[#This Row],[gross_revenue]]-Table1[[#This Row],[cost_of_goods]] -> 3612.4493 | AO7: =Table1[[#This Row],[scenario_revenue]]-Table1[[#This Row],[Scenario_unit_cost]] -> 4465.0944 | AP7: =IF(Table1[[#This Row],[gross_revenue]]=0,0,Table1[[#This Row],[gross_profit]]/Table1[[#This Row],[gross_revenue]]) -> 0.14878997
A8: ORD-2024-921935 | B8: =_xlfn.TEXTAFTER(Table1[[#This Row],[OrderID]],"-",2) -> 921935 | C8: =YEAR(Table1[[#This Row],[OrderDate]]) -> 2024 | D8: =_xlfn.MINIFS(F:F,P:P,Table1[[#This Row],[Country]]) -> 44945 | E8: =DATEDIF(Table1[[#This Row],[first_time_orders]],Table1[[#This Row],[OrderDate]],"m") -> 11 | F8: 45292 | G8: =TEXT(Table1[[#This Row],[OrderDate]],"MMM-YYYY") -> Jan-2024 | H8: =MONTH(Table1[[#This Row],[OrderDate]]) -> 1 | I8: ="Q"&ROUNDUP(Table1[[#This Row],[months]]/3,0)&"-"&Table1[[#This Row],[order_year]] -> Q1-2024 | J8: =Table1[[#This Row],[RequiredDate]]-Table1[[#This Row],[OrderDate]] -> 26 | K8: =IF(Table1[[#This Row],[lead_time]]<0,MEDIAN(J:J),Table1[[#This Row],[lead_time]]) -> 26 | L8: =IF(Table1[[#This Row],[adj_lead_time]]<=7,1,0) -> 0 | M8: 45318 | N8: =IF(Table1[[#This Row],[lead_time]]<0,(Table1[[#This Row],[OrderDate]]+Table1[[#This Row],[adj_lead_time]]),Table1[[#This Row],[RequiredDate]]) -> 45318 | O8: Europe | P8: United Kingdom | Q8: Manchester | R8: Education | S8: Distributor | T8: D. Smith | U8: Accessories | V8: ACC-3103 | W8: 657.45 | X8: =Table1[[#This Row],[UnitCost]]*(1+'scenario modeling'!$B$3) -> 723.195 | Y8: 1325.96 | Z8: =IF(Table1[[#This Row],[UnitPrice]]<=Quantiles!$B$2,Quantiles!$A$2,IF(Table1[[#This Row],[UnitPrice]]<=Quantiles!$B$3,Quantiles!$A$3,Quantiles!$A$4)) -> Medium | AA8: 0.167 | AB8: =MIN(Table1[[#This Row],[DiscountPct]],'scenario modeling'!$B$2) -> 0.1 | AC8: =IF(Table1[[#This Row],[DiscountPct]]>0.3, ">0.3","") | AD8: 21 | AE8: =Table1[[#This Row],[Quantity]]*(1+'scenario modeling'!$B$4) -> 25.2 | AF8: =Table1[[#This Row],[UnitCost]]*Table1[[#This Row],[Quantity]] -> 13806.45 | AG8: =SUMIF($U:U,Table1[[#This Row],[ProductCategory]],$AM:AM) -> 1331102.9 | AH8: =SUMIFS($AM$2:AM8,$U$2:U8,U8) -> 136123.94 | AI8: =Table1[[#This Row],[Cumulative_revenue]]/Table1[[#This Row],[Category_revenue]] -> 0.10226402 | AJ8: =IF(Table1[[#This Row],[cumulative_pct]]<=0.8,"A",IF(Table1[[#This Row],[cumulative_pct]]<=0.95,"B","C")) -> A | AK8: =Table1[[#This Row],[adj_unit_cost]]*Table1[[#This Row],[scenario_quantity]] -> 18224.514 | AL8: =Table1[[#This Row],[UnitPrice]]*Table1[[#This Row],[scenario_quantity]]*(1-Table1[[#This Row],[cap_adjusted_discount]]) -> 30072.773 | AM8: =Table1[[#This Row],[UnitPrice]]*Table1[[#This Row],[Quantity]]*(1-Table1[[#This Row],[DiscountPct]]) -> 23195.018 | AN8: =Table1[[#This Row],[gross_revenue]]-Table1[[#This Row],[cost_of_goods]] -> 9388.5683 | AO8: =Table1[[#This Row],[scenario_revenue]]-Table1[[#This Row],[Scenario_unit_cost]] -> 11848.259 | AP8: =IF(Table1[[#This Row],[gross_revenue]]=0,0,Table1[[#This Row],[gross_profit]]/Table1[[#This Row],[gross_revenue]]) -> 0.40476658
A9: ORD-2024-277241 | B9: =_xlfn.TEXTAFTER(Table1[[#This Row],[OrderID]],"-",2) -> 277241 | C9: =YEAR(Table1[[#This Row],[OrderDate]]) -> 2024 | D9: =_xlfn.MINIFS(F:F,P:P,Table1[[#This Row],[Country]]) -> 44933 | E9: =DATEDIF(Table1[[#This Row],[first_time_orders]],Table1[[#This Row],[OrderDate]],"m") -> 12 | F9: 45319 | G9: =TEXT(Table1[[#This Row],[OrderDate]],"MMM-YYYY") -> Jan-2024 | H9: =MONTH(Table1[[#This Row],[OrderDate]]) -> 1 | I9: ="Q"&ROUNDUP(Table1[[#This Row],[months]]/3,0)&"-"&Table1[[#This Row],[order_year]] -> Q1-2024 | J9: =Table1[[#This Row],[RequiredDate]]-Table1[[#This Row],[OrderDate]] -> 2 | K9: =IF(Table1[[#This Row],[lead_time]]<0,MEDIAN(J:J),Table1[[#This Row],[lead_time]]) -> 2 | L9: =IF(Table1[[#This Row],[adj_lead_time]]<=7,1,0) -> 1 | M9: 45321 | N9: =IF(Table1[[#This Row],[lead_time]]<0,(Table1[[#This Row],[OrderDate]]+Table1[[#This Row],[adj_lead_time]]),Table1[[#This Row],[RequiredDate]]) -> 45321 | O9: Africa | P9: South Africa | Q9: Cape Town | R9: Consumer | S9: Direct | T9: F. Müller | U9: Accessories | V9: ACC-6223 | W9: 798.45 | X9: =Table1[[#This Row],[UnitCost]]*(1+'scenario modeling'!$B$3) -> 878.295 | Y9: 1592.02 | Z9: =IF(Table1[[#This Row],[UnitPrice]]<=Quantiles!$B$2,Quantiles!$A$2,IF(Table1[[#This Row],[UnitPrice]]<=Quantiles!$B$3,Quantiles!$A$3,Quantiles!$A$4)) -> Medium | AA9: 0.066 | AB9: =MIN(Table1[[#This Row],[DiscountPct]],'scenario modeling'!$B$2) -> 0.066 | AC9: =IF(Table1[[#This Row],[DiscountPct]]>0.3, ">0.3","") | AD9: 18 | AE9: =Table1[[#This Row],[Quantity]]*(1+'scenario modeling'!$B$4) -> 21.6 | AF9: =Table1[[#This Row],[UnitCost]]*Table1[[#This Row],[Quantity]] -> 14372.1 | AG9: =SUMIF($U:U,Table1[[#This Row],[ProductCategory]],$AM:AM) -> 1331102.9 | AH9: =SUMIFS($AM$2:AM9,$U$2:U9,U9) -> 162888.98 | AI9: =Table1[[#This Row],[Cumulative_revenue]]/Table1[[#This Row],[Category_revenue]] -> 0.12237143 | AJ9: =IF(Table1[[#This Row],[cumulative_pct]]<=0.8,"A",IF(Table1[[#This Row],[cumulative_pct]]<=0.95,"B","C")) -> A | AK9: =Table1[[#This Row],[adj_unit_cost]]*Table1[[#This Row],[scenario_quantity]] -> 18971.172 | AL9: =Table1[[#This Row],[UnitPrice]]*Table1[[#This Row],[scenario_quantity]]*(1-Table1[[#This Row],[cap_adjusted_discount]]) -> 32118.048 | AM9: =Table1[[#This Row],[UnitPrice]]*Table1[[#This Row],[Quantity]]*(1-Table1[[#This Row],[DiscountPct]]) -> 26765.04 | AN9: =Table1[[#This Row],[gross_revenue]]-Table1[[#This Row],[cost_of_goods]] -> 12392.94 | AO9: =Table1[[#This Row],[scenario_revenue]]-Table1[[#This Row],[Scenario_unit_cost]] -> 13146.876 | AP9: =IF(Table1[[#This Row],[gross_revenue]]=0,0,Table1[[#This Row],[gross_profit]]/Table1[[#This Row],[gross_revenue]]) -> 0.46302715
A10: ORD-2024-210687 | B10: =_xlfn.TEXTAFTER(Table1[[#This Row],[OrderID]],"-",2) -> 210687 | C10: =YEAR(Table1[[#This Row],[OrderDate]]) -> 2024 | D10: =_xlfn.MINIFS(F:F,P:P,Table1[[#This Row],[Country]]) -> 44948 | E10: =DATEDIF(Table1[[#This Row],[first_time_orders]],Table1[[#This Row],[OrderDate]],"m") -> 12 | F10: 45319 | G10: =TEXT(Table1[[#This Row],[OrderDate]],"MMM-YYYY") -> Jan-2024 | H10: =MONTH(Table1[[#This Row],[OrderDate]]) -> 1 | I10: ="Q"&ROUNDUP(Table1[[#This Row],[months]]/3,0)&"-"&Table1[[#This Row],[order_year]] -> Q1-2024 | J10: =Table1[[#This Row],[RequiredDate]]-Table1[[#This Row],[OrderDate]] -> 12 | K10: =IF(Table1[[#This Row],[lead_time]]<0,MEDIAN(J:J),Table1[[#This Row],[lead_time]]) -> 12 | L10: =IF(Table1[[#This Row],[adj_lead_time]]<=7,1,0) -> 0 | M10: 45331 | N10: =IF(Table1[[#This Row],[lead_time]]<0,(Table1[[#This Row],[OrderDate]]+Table1[[#This Row],[adj_lead_time]]),Table1[[#This Row],[RequiredDate]]) -> 45331 | O10: Europe | P10: Germany | Q10: Berlin | R10: Corporate | S10: Online | T10: G. Dubois | U10: Accessories | V10: ACC-7938 | W10: 644.17 | X10: =Table1[[#This Row],[UnitCost]]*(1+'scenario modeling'!$B$3) -> 708.587 | Y10: 700.12 | Z10: =IF(Table1[[#This Row],[UnitPrice]]<=Quantiles!$B$2,Quantiles!$A$2,IF(Table1[[#This Row],[UnitPrice]]<=Quantiles!$B$3,Quantiles!$A$3,Quantiles!$A$4)) -> Low | AA10: 0.006 | AB10: =MIN(Table1[[#This Row],[DiscountPct]],'scenario modeling'!$B$2) -> 0.006 | AC10: =IF(Table1[[#This Row],[DiscountPct]]>0.3, ">0.3","") | AD10: 23 | AE10: =Table1[[#This Row],[Quantity]]*(1+'scenario modeling'!$B$4) -> 27.6 | AF10: =Table1[[#This Row],[UnitCost]]*Table1[[#This Row],[Quantity]] -> 14815.91 | AG10: =SUMIF($U:U,Table1[[#This Row],[ProductCategory]],$AM:AM) -> 1331102.9 | AH10: =SUMIFS($AM$2:AM10,$U$2:U10,U10) -> 178895.12 | AI10: =Table1[[#This Row],[Cumulative_revenue]]/Table1[[#This Row],[Category_revenue]] -> 0.13439616 | AJ10: =IF(Table1[[#This Row],[cumulative_pct]]<=0.8,"A",IF(Table1[[#This Row],[cumulative_pct]]<=0.95,"B","C")) -> A | AK10: =Table1[[#This Row],[adj_unit_cost]]*Table1[[#This Row],[scenario_quantity]] -> 19557.001 | AL10: =Table1[[#This Row],[UnitPrice]]*Table1[[#This Row],[scenario_quantity]]*(1-Table1[[#This Row],[cap_adjusted_discount]]) -> 19207.372 | AM10: =Table1[[#This Row],[UnitPrice]]*Table1[[#This Row],[Quantity]]*(1-Table1[[#This Row],[DiscountPct]]) -> 16006.143 | AN10: =Table1[[#This Row],[gross_revenue]]-Table1[[#This Row],[cost_of_goods]] -> 1190.2334 | AO10: =Table1[[#This Row],[scenario_revenue]]-Table1[[#This Row],[Scenario_unit_cost]] -> -349.62907 | AP10: =IF(Table1[[#This Row],[gross_revenue]]=0,0,Table1[[#This Row],[gross_profit]]/Table1[[#This Row],[gross_revenue]]) -> 0.074361038
A11: ORD-2024-232632 | B11: =_xlfn.TEXTAFTER(Table1[[#This Row],[OrderID]],"-",2) -> 232632 | C11: =YEAR(Table1[[#This Row],[OrderDate]]) -> 2024 | D11: =_xlfn.MINIFS(F:F,P:P,Table1[[#This Row],[Country]]) -> 44938 | E11: =DATEDIF(Table1[[#This Row],[first_time_orders]],Table1[[#This Row],[OrderDate]],"m") -> 13 | F11: 45336 | G11: =TEXT(Table1[[#This Row],[OrderDate]],"MMM-YYYY") -> Feb-2024 | H11: =MONTH(Table1[[#This Row],[OrderDate]]) -> 2 | I11: ="Q"&ROUNDUP(Table1[[#This Row],[months]]/3,0)&"-"&Table1[[#This Row],[order_year]] -> Q1-2024 | J11: =Table1[[#This Row],[RequiredDate]]-Table1[[#This Row],[OrderDate]] -> 0 | K11: =IF(Table1[[#This Row],[lead_time]]<0,MEDIAN(J:J),Table1[[#This Row],[lead_time]]) -> 0 | L11: =IF(Table1[[#This Row],[adj_lead_time]]<=7,1,0) -> 1 | M11: 45336 | N11: =IF(Table1[[#This Row],[lead_time]]<0,(Table1[[#This Row],[OrderDate]]+Table1[[#This Row],[adj_lead_time]]),Table1[[#This Row],[RequiredDate]]) -> 45336 | O11: Asia | P11: China | Q11: Beijing | R11: Corporate | S11: Distributor | T11: L. Okafor | U11: Accessories | V11: ACC-1021 | W11: 65.93 | X11: =Table1[[#This Row],[UnitCost]]*(1+'scenario modeling'!$B$3) -> 72.523 | Y11: 84.9 | Z11: =IF(Table1[[#This Row],[UnitPrice]]<=Quantiles!$B$2,Quantiles!$A$2,IF(Table1[[#This Row],[UnitPrice]]<=Quantiles!$B$3,Quantiles!$A$3,Quantiles!$A$4)) -> Low | AA11: 0.259 | AB11: =MIN(Table1[[#This Row],[DiscountPct]],'scenario modeling'!$B$2) -> 0.1 | AC11: =IF(Table1[[#This Row],[DiscountPct]]>0.3, ">0.3","") | AD11: 23 | AE11: =Table1[[#This Row],[Quantity]]*(1+'scenario modeling'!$B$4) -> 27.6 | AF11: =Table1[[#This Row],[UnitCost]]*Table1[[#This Row],[Quantity]] -> 1516.39 | AG11: =SUMIF($U:U,Table1[[#This Row],[ProductCategory]],$AM:AM) -> 1331102.9 | AH11: =SUMIFS($AM$2:AM11,$U$2:U11,U11) -> 180342.07 | AI11: =Table1[[#This Row],[Cumulative_revenue]]/Table1[[#This Row],[Category_revenue]] -> 0.13548319 | AJ11: =IF(Table1[[#This Row],[cumulative_pct]]<=0.8,"A",IF(Table1[[#This Row],[cumulative_pct]]<=0.95,"B","C")) -> A | AK11: =Table1[[#This Row],[adj_unit_cost]]*Table1[[#This Row],[scenario_quantity]] -> 2001.6348 | AL11: =Table1[[#This Row],[UnitPrice]]*Table1[[#This Row],[scenario_quantity]]*(1-Table1[[#This Row],[cap_adjusted_discount]]) -> 2108.916 | AM11: =Table1[[#This Row],[UnitPrice]]*Table1[[#This Row],[Quantity]]*(1-Table1[[#This Row],[DiscountPct]]) -> 1446.9507 | AN11: =Table1[[#This Row],[gross_revenue]]-Table1[[#This Row],[cost_of_goods]] -> -69.4393 | AO11: =Table1[[#This Row],[scenario_revenue]]-Table1[[#This Row],[Scenario_unit_cost]] -> 107.2812 | AP11: =IF(Table1[[#This Row],[gross_revenue]]=0,0,Table1[[#This Row],[gross_profit]]/Table1[[#This Row],[gross_revenue]]) -> -0.047990094
A12: ORD-2024-287210 | B12: =_xlfn.TEXTAFTER(Table1[[#This Row],[OrderID]],"-",2) -> 287210 | C12: =YEAR(Table1[[#This Row],[OrderDate]]) -> 2024 | D12: =_xlfn.MINIFS(F:F,P:P,Table1[[#This Row],[Country]]) -> 44948 | E12: =DATEDIF(Table1[[#This Row],[first_time_orders]],Table1[[#This Row],[OrderDate]],"m") -> 13 | F12: 45369 | G12: =TEXT(Table1[[#This Row],[OrderDate]],"MMM-YYYY") -> Mar-2024 | H12: =MONTH(Table1[[#This Row],[OrderDate]]) -> 3 | I12: ="Q"&ROUNDUP(Table1[[#This Row],[months]]/3,0)&"-"&Table1[[#This Row],[order_year]] -> Q1-2024 | J12: =Table1[[#This Row],[RequiredDate]]-Table1[[#This Row],[OrderDate]] -> 3 | K12: =IF(Table1[[#This Row],[lead_time]]<0,MEDIAN(J:J),Table1[[#This Row],[lead_time]]) -> 3 | L12: =IF(Table1[[#This Row],[adj_lead_time]]<=7,1,0) -> 1 | M12: 45372 | N12: =IF(Table1[[#This Row],[lead_time]]<0,(Table1[[#This Row],[OrderDate]]+Table1[[#This Row],[adj_lead_time]]),Table1[[#This Row],[RequiredDate]]) -> 45372 | O12: Europe | P12: Germany | Q12: Munich | R12: Small Business | S12: Online | T12: M. Rossi | U12: Accessories | V12: ACC-2761 | W12: 910.63 | X12: =Table1[[#This Row],[UnitCost]]*(1+'scenario modeling'!$B$3) -> 1001.693 | Y12: 1269.4 | Z12: =IF(Table1[[#This Row],[UnitPrice]]<=Quantiles!$B$2,Quantiles!$A$2,IF(Table1[[#This Row],[UnitPrice]]<=Quantiles!$B$3,Quantiles!$A$3,Quantiles!$A$4)) -> Medium | AA12: 0.068 | AB12: =MIN(Table1[[#This Row],[DiscountPct]],'scenario modeling'!$B$2) -> 0.068 | AC12: =IF(Table1[[#This Row],[DiscountPct]]>0.3, ">0.3","") | AD12: 9 | AE12: =Table1[[#This Row],[Quantity]]*(1+'scenario modeling'!$B$4) -> 10.8 | AF12: =Table1[[#This Row],[UnitCost]]*Table1[[#This Row],[Quantity]] -> 8195.67 | AG12: =SUMIF($U:U,Table1[[#This Row],[ProductCategory]],$AM:AM) -> 1331102.9 | AH12: =SUMIFS($AM$2:AM12,$U$2:U12,U12) -> 190989.8 | AI12: =Table1[[#This Row],[Cumulative_revenue]]/Table1[[#This Row],[Category_revenue]] -> 0.14348236 | AJ12: =IF(Table1[[#This Row],[cumulative_pct]]<=0.8,"A",IF(Table1[[#This Row],[cumulative_pct]]<=0.95,"B","C")) -> A | AK12: =Table1[[#This Row],[adj_unit_cost]]*Table1[[#This Row],[scenario_quantity]] -> 10818.284 | AL12: =Table1[[#This Row],[UnitPrice]]*Table1[[#This Row],[scenario_quantity]]*(1-Table1[[#This Row],[cap_adjusted_discount]]) -> 12777.273 | AM12: =Table1[[#This Row],[UnitPrice]]*Table1[[#This Row],[Quantity]]*(1-Table1[[#This Row],[DiscountPct]]) -> 10647.727 | AN12: =Table1[[#This Row],[gross_revenue]]-Table1[[#This Row],[cost_of_goods]] -> 2452.0572 | AO12: =Table1[[#This Row],[scenario_revenue]]-Table1[[#This Row],[Scenario_unit_cost]] -> 1958.9882 | AP12: =IF(Table1[[#This Row],[gross_revenue]]=0,0,Table1[[#This Row],[gross_profit]]/Table1[[#This Row],[gross_revenue]]) -> 0.23028926
A13: ORD-2024-211453 | B13: =_xlfn.TEXTAFTER(Table1[[#This Row],[OrderID]],"-",2) -> 211453 | C13: =YEAR(Table1[[#This Row],[OrderDate]]) -> 2024 | D13: =_xlfn.MINIFS(F:F,P:P,Table1[[#This Row],[Country]]) -> 44948 | E13: =DATEDIF(Table1[[#This Row],[first_time_orders]],Table1[[#This Row],[OrderDate]],"m") -> 14 | F13: 45386 | G13: =TEXT(Table1[[#This Row],[OrderDate]],"MMM-YYYY") -> Apr-2024 | H13: =MONTH(Table1[[#This Row],[OrderDate]]) -> 4 | I13: ="Q"&ROUNDUP(Table1[[#This Row],[months]]/3,0)&"-"&Table1[[#This Row],[order_year]] -> Q2-2024 | J13: =Table1[[#This Row],[RequiredDate]]-Table1[[#This Row],[OrderDate]] -> 20 | K13: =IF(Table1[[#This Row],[lead_time]]<0,MEDIAN(J:J),Table1[[#This Row],[lead_time]]) -> 20 | L13: =IF(Table1[[#This Row],[adj_lead_time]]<=7,1,0) -> 0 | M13: 45406 | N13: =IF(Table1[[#This Row],[lead_time]]<0,(Table1[[#This Row],[OrderDate]]+Table1[[#This Row],[adj_lead_time]]),Table1[[#This Row],[RequiredDate]]) -> 45406 | O13: Europe | P13: Germany | Q13: Frankfurt | R13: Non-Profit | S13: Direct | T13: O. Wang | U13: Accessories | V13: ACC-6543 | W13: 683.42 | X13: =Table1[[#This Row],[UnitCost]]*(1+'scenario modeling'!$B$3) -> 751.762 | Y13: 951.51 | Z13: =IF(Table1[[#This Row],[UnitPrice]]<=Quantiles!$B$2,Quantiles!$A$2,IF(Table1[[#This Row],[UnitPrice]]<=Quantiles!$B$3,Quantiles!$A$3,Quantiles!$A$4)) -> Medium | AA13: 0 | AB13: =MIN(Table1[[#This Row],[DiscountPct]],'scenario modeling'!$B$2) -> 0 | AC13: =IF(Table1[[#This Row],[DiscountPct]]>0.3, ">0.3","") | AD13: 14 | AE13: =Table1[[#This Row],[Quantity]]*(1+'scenario modeling'!$B$4) -> 16.8 | AF13: =Table1[[#This Row],[UnitCost]]*Table1[[#This Row],[Quantity]] -> 9567.88 | AG13: =SUMIF($U:U,Table1[[#This Row],[ProductCategory]],$AM:AM) -> 1331102.9 | AH13: =SUMIFS($AM$2:AM13,$U$2:U13,U13) -> 204310.94 | AI13: =Table1[[#This Row],[Cumulative_revenue]]/Table1[[#This Row],[Category_revenue]] -> 0.15348996 | AJ13: =IF(Table1[[#This Row],[cumulative_pct]]<=0.8,"A",IF(Table1[[#This Row],[cumulative_pct]]<=0.95,"B","C")) -> A | AK13: =Table1[[#This Row],[adj_unit_cost]]*Table1[[#This Row],[scenario_quantity]] -> 12629.602 | AL13: =Table1[[#This Row],[UnitPrice]]*Table1[[#This Row],[scenario_quantity]]*(1-Table1[[#This Row],[cap_adjusted_discount]]) -> 15985.368 | AM13: =Table1[[#This Row],[UnitPrice]]*Table1[[#This Row],[Quantity]]*(1-Table1[[#This Row],[DiscountPct]]) -> 13321.14 | AN13: =Table1[[#This Row],[gross_revenue]]-Table1[[#This Row],[cost_of_goods]] -> 3753.26 | AO13: =Table1[[#This Row],[scenario_revenue]]-Table1[[#This Row],[Scenario_unit_cost]] -> 3355.7664 | AP13: =IF(Table1[[#This Row],[gross_revenue]]=0,0,Table1[[#This Row],[gross_profit]]/Table1[[#This Row],[gross_revenue]]) -> 0.28175216
... A633: ORD-2023-596758 | B633: =_xlfn.TEXTAFTER(Table1[[#This Row],[OrderID]],"-",2) -> 596758 | C633: =YEAR(Table1[[#This Row],[OrderDate]]) -> 2023 | D633: =_xlfn.MINIFS(F:F,P:P,Table1[[#This Row],[Country]]) -> 44988 | E633: =DATEDIF(Table1[[#This Row],[first_time_orders]],Table1[[#This Row],[OrderDate]],"m") -> 9 | F633: 45267 | G633: =TEXT(Table1[[#This Row],[OrderDate]],"MMM-YYYY") -> Dec-2023 | H633: =MONTH(Table1[[#This Row],[OrderDate]]) -> 12 | I633: ="Q"&ROUNDUP(Table1[[#This Row],[months]]/3,0)&"-"&Table1[[#This Row],[order_year]] -> Q4-2023 | J633: =Table1[[#This Row],[RequiredDate]]-Table1[[#This Row],[OrderDate]] -> -2 | K633: =IF(Table1[[#This Row],[lead_time]]<0,MEDIAN(J:J),Table1[[#This Row],[lead_time]]) -> 15 | L633: =IF(Table1[[#This Row],[adj_lead_time]]<=7,1,0) -> 0 | M633: 45265 | N633: =IF(Table1[[#This Row],[lead_time]]<0,(Table1[[#This Row],[OrderDate]]+Table1[[#This Row],[adj_lead_time]]),Table1[[#This Row],[RequiredDate]]) -> 45282 | O633: Asia | P633: Japan | Q633: Tokyo | R633: Non-Profit | S633: Marketplace | T633: H. Kim | U633: Printers | V633: PRN-8175 | W633: 1097.59 | X633: =Table1[[#This Row],[UnitCost]]*(1+'scenario modeling'!$B$3) -> 1207.349 | Y633: 845.55 | Z633: =IF(Table1[[#This Row],[UnitPrice]]<=Quantiles!$B$2,Quantiles!$A$2,IF(Table1[[#This Row],[UnitPrice]]<=Quantiles!$B$3,Quantiles!$A$3,Quantiles!$A$4)) -> Medium | AA633: 0.184 | AB633: =MIN(Table1[[#This Row],[DiscountPct]],'scenario modeling'!$B$2) -> 0.1 | AC633: =IF(Table1[[#This Row],[DiscountPct]]>0.3, ">0.3","") | AD633: 6 | AE633: =Table1[[#This Row],[Quantity]]*(1+'scenario modeling'!$B$4) -> 7.2 | AF633: =Table1[[#This Row],[UnitCost]]*Table1[[#This Row],[Quantity]] -> 6585.54 | AG633: =SUMIF($U:U,Table1[[#This Row],[ProductCategory]],$AM:AM) -> 1616102.7 | AH633: =SUMIFS($AM$2:AM633,$U$2:U633,U633) -> 1616102.7 | AI633: =Table1[[#This Row],[Cumulative_revenue]]/Table1[[#This Row],[Category_revenue]] -> 1 | AJ633: =IF(Table1[[#This Row],[cumulative_pct]]<=0.8,"A",IF(Table1[[#This Row],[cumulative_pct]]<=0.95,"B","C")) -> C | AK633: =Table1[[#This Row],[adj_unit_cost]]*Table1[[#This Row],[scenario_quantity]] -> 8692.9128 | AL633: =Table1[[#This Row],[UnitPrice]]*Table1[[#This Row],[scenario_quantity]]*(1-Table1[[#This Row],[cap_adjusted_discount]]) -> 5479.164 | AM633: =Table1[[#This Row],[UnitPrice]]*Table1[[#This Row],[Quantity]]*(1-Table1[[#This Row],[DiscountPct]]) -> 4139.8128 | AN633: =Table1[[#This Row],[gross_revenue]]-Table1[[#This Row],[cost_of_goods]] -> -2445.7272 | AO633: =Table1[[#This Row],[scenario_revenue]]-Table1[[#This Row],[Scenario_unit_cost]] -> -3213.7488 | AP633: =IF(Table1[[#This Row],[gross_revenue]]=0,0,Table1[[#This Row],[gross_profit]]/Table1[[#This Row],[gross_revenue]]) -> -0.59078208

Sheet scenario modeling
A1: Sceneraio Controls | B1: Values | F1: BASELINE REVENUE | G1: =SUM(clean_data!AM:AM) -> 10925968
A2: Global Discount Cap | B2: 0.1 | F2: BASELINE_PROFIT | G2: =SUM(clean_data!AN:AN) -> 3398219.9
A3: Unit Cost Inflation | B3: 0.1 | F3: MODELED_REVENUE | G3: =SUM(clean_data!AL:AL) -> 13790153
A4: Quantity Uplift | B4: 0.2 | F4: MODELED_PROFIT | G4: =SUM(clean_data!AO:AO) -> 3853525.8

Sheet lead_proxy
A1: {=_xlfn.UNIQUE(clean_data!P:P)} -> Country | B1: order count | C1: orders<=7days | D1: %<=7days
A2: Nigeria | B2: =COUNTIF(clean_data!P:P,lead_proxy!A2) -> 44 | C2: =SUMIF(clean_data!P:P,lead_proxy!A2,clean_data!L:L) -> 14 | D2: =C2/B2 -> 0.31818182
A3: India | B3: =COUNTIF(clean_data!P:P,lead_proxy!A3) -> 61 | C3: =SUMIF(clean_data!P:P,lead_proxy!A3,clean_data!L:L) -> 11 | D3: =C3/B3 -> 0.18032787
A4: United Kingdom | B4: =COUNTIF(clean_data!P:P,lead_proxy!A4) -> 54 | C4: =SUMIF(clean_data!P:P,lead_proxy!A4,clean_data!L:L) -> 13 | D4: =C4/B4 -> 0.24074074
A5: Japan | B5: =COUNTIF(clean_data!P:P,lead_proxy!A5) -> 59 | C5: =SUMIF(clean_data!P:P,lead_proxy!A5,clean_data!L:L) -> 10 | D5: =C5/B5 -> 0.16949153
A6: China | B6: =COUNTIF(clean_data!P:P,lead_proxy!A6) -> 51 | C6: =SUMIF(clean_data!P:P,lead_proxy!A6,clean_data!L:L) -> 9 | D6: =C6/B6 -> 0.17647059
A7: France | B7: =COUNTIF(clean_data!P:P,lead_proxy!A7) -> 54 | C7: =SUMIF(clean_data!P:P,lead_proxy!A7,clean_data!L:L) -> 12 | D7: =C7/B7 -> 0.22222222
A8: South Africa | B8: =COUNTIF(clean_data!P:P,lead_proxy!A8) -> 45 | C8: =SUMIF(clean_data!P:P,lead_proxy!A8,clean_data!L:L) -> 10 | D8: =C8/B8 -> 0.22222222
A9: Germany | B9: =COUNTIF(clean_data!P:P,lead_proxy!A9) -> 51 | C9: =SUMIF(clean_data!P:P,lead_proxy!A9,clean_data!L:L) -> 11 | D9: =C9/B9 -> 0.21568627
A10: Kenya | B10: =COUNTIF(clean_data!P:P,lead_proxy!A10) -> 56 | C10: =SUMIF(clean_data!P:P,lead_proxy!A10,clean_data!L:L) -> 15 | D10: =C10/B10 -> 0.26785714
A11: Brazil | B11: =COUNTIF(clean_data!P:P,lead_proxy!A11) -> 62 | C11: =SUMIF(clean_data!P:P,lead_proxy!A11,clean_data!L:L) -> 13 | D11: =C11/B11 -> 0.20967742
A12: Canada | B12: =COUNTIF(clean_data!P:P,lead_proxy!A12) -> 44 | C12: =SUMIF(clean_data!P:P,lead_proxy!A12,clean_data!L:L) -> 6 | D12: =C12/B12 -> 0.13636364
A13: USA | B13: =COUNTIF(clean_data!P:P,lead_proxy!A13) -> 51 | C13: =SUMIF(clean_data!P:P,lead_proxy!A13,clean_data!L:L) -> 14 | D13: =C13/B13 -> 0.2745098
A14: 0
A17: {=_xlfn.UNIQUE(clean_data!U:U)} -> ProductCategory | B17: order count | C17: orders<=7days | D17: %<=7days
A18: Accessories | B18: =COUNTIF(clean_data!U:U,lead_proxy!A18) -> 88 | C18: =SUMIF(Table1[ProductCategory],lead_proxy!A18,clean_data!L:L) -> 28 | D18: =C18/B18 -> 0.31818182
A19: Components | B19: =COUNTIF(clean_data!U:U,lead_proxy!A19) -> 91 | C19: =SUMIF(Table1[ProductCategory],lead_proxy!A19,clean_data!L:L) -> 19 | D19: =C19/B19 -> 0.20879121
A20: Laptops | B20: =COUNTIF(clean_data!U:U,lead_proxy!A20) -> 82 | C20: =SUMIF(Table1[ProductCategory],lead_proxy!A20,clean_data!L:L) -> 24 | D20: =C20/B20 -> 0.29268293
A21: Monitors | B21: =COUNTIF(clean_data!U:U,lead_proxy!A21) -> 94 | C21: =SUMIF(Table1[ProductCategory],lead_proxy!A21,clean_data!L:L) -> 14 | D21: =C21/B21 -> 0.14893617
A22: Networking | B22: =COUNTIF(clean_data!U:U,lead_proxy!A22) -> 86 | C22: =SUMIF(Table1[ProductCategory],lead_proxy!A22,clean_data!L:L) -> 18 | D22: =C22/B22 -> 0.20930233
A23: Phones | B23: =COUNTIF(clean_data!U:U,lead_proxy!A23) -> 88 | C23: =SUMIF(Table1[ProductCategory],lead_proxy!A23,clean_data!L:L) -> 15 | D23: =C23/B23 -> 0.17045455
A24: Printers | B24: =COUNTIF(clean_data!U:U,lead_proxy!A24) -> 103 | C24: =SUMIF(Table1[ProductCategory],lead_proxy!A24,clean_data!L:L) -> 20 | D24: =C24/B24 -> 0.19417476
A25: 0

Sheet sales
A1: {=_xlfn.UNIQUE(clean_data!T1:T633)} -> Salesperson | B1: Order_count | C1: First_order_date | D1: last_order_date | E1: operations_duration | F1: revenue | G1: profits | H1: average_discount | I1: Orders/month | J1: revenue/order | K1: profit/order
A2: D. Smith | B2: =COUNTIF(clean_data!T:T,sales!A2) -> 39 | C2: =_xlfn.MINIFS(clean_data!F:F,clean_data!T:T,sales!A2) -> 44936 | D2: =_xlfn.MAXIFS(clean_data!F:F,clean_data!T:T,sales!A2) -> 45914 | E2: =DATEDIF(C2,D2,"m") -> 32 | F2: =SUMIF(clean_data!T:T,sales!A2,clean_data!AM:AM) -> 614644.3 | G2: =SUMIF(clean_data!T:T,sales!A2,clean_data!AN:AN) -> 170472.52 | H2: =AVERAGEIF(Table1[Salesperson],sales!A2,clean_data!AA:AA) -> 0.11978947 | I2: =B2/E2 -> 1.21875 | J2: =F2/B2 -> 15760.11 | K2: =G2/B2 -> 4371.0903
A3: B. Chen | B3: =COUNTIF(clean_data!T:T,sales!A3) -> 48 | C3: =_xlfn.MINIFS(clean_data!F:F,clean_data!T:T,sales!A3) -> 44928 | D3: =_xlfn.MAXIFS(clean_data!F:F,clean_data!T:T,sales!A3) -> 45894 | E3: =DATEDIF(C3,D3,"m") -> 31 | F3: =SUMIF(clean_data!T:T,sales!A3,clean_data!AM:AM) -> 893735.66 | G3: =SUMIF(clean_data!T:T,sales!A3,clean_data!AN:AN) -> 315969.97 | H3: =AVERAGEIF(Table1[Salesperson],sales!A3,clean_data!AA:AA) -> 0.1291875 | I3: =B3/E3 -> 1.5483871 | J3: =F3/B3 -> 18619.493 | K3: =G3/B3 -> 6582.7077
A4: G. Dubois | B4: =COUNTIF(clean_data!T:T,sales!A4) -> 30 | C4: =_xlfn.MINIFS(clean_data!F:F,clean_data!T:T,sales!A4) -> 44945 | D4: =_xlfn.MAXIFS(clean_data!F:F,clean_data!T:T,sales!A4) -> 45858 | E4: =DATEDIF(C4,D4,"m") -> 30 | F4: =SUMIF(clean_data!T:T,sales!A4,clean_data!AM:AM) -> 510653.71 | G4: =SUMIF(clean_data!T:T,sales!A4,clean_data!AN:AN) -> 172441.87 | H4: =AVERAGEIF(Table1[Salesperson],sales!A4,clean_data!AA:AA) -> 0.12106667 | I4: =B4/E4 -> 1 | J4: =F4/B4 -> 17021.79 | K4: =G4/B4 -> 5748.0624
A5: A. Patel | B5: =COUNTIF(clean_data!T:T,sales!A5) -> 48 | C5: =_xlfn.MINIFS(clean_data!F:F,clean_data!T:T,sales!A5) -> 44933 | D5: =_xlfn.MAXIFS(clean_data!F:F,clean_data!T:T,sales!A5) -> 45915 | E5: =DATEDIF(C5,D5,"m") -> 32 | F5: =SUMIF(clean_data!T:T,sales!A5,clean_data!AM:AM) -> 1005389.1 | G5: =SUMIF(clean_data!T:T,sales!A5,clean_data!AN:AN) -> 337634.71 | H5: =AVERAGEIF(Table1[Salesperson],sales!A5,clean_data!AA:AA) -> 0.11516667 | I5: =B5/E5 -> 1.5 | J5: =F5/B5 -> 20945.606 | K5: =G5/B5 -> 7034.0564
A6: L. Okafor | B6: =COUNTIF(clean_data!T:T,sales!A6) -> 49 | C6: =_xlfn.MINIFS(clean_data!F:F,clean_data!T:T,sales!A6) -> 44962 | D6: =_xlfn.MAXIFS(clean_data!F:F,clean_data!T:T,sales!A6) -> 45915 | E6: =DATEDIF(C6,D6,"m") -> 31 | F6: =SUMIF(clean_data!T:T,sales!A6,clean_data!AM:AM) -> 904189.82 | G6: =SUMIF(clean_data!T:T,sales!A6,clean_data!AN:AN) -> 285453.56 | H6: =AVERAGEIF(Table1[Salesperson],sales!A6,clean_data!AA:AA) -> 0.10359184 | I6: =B6/E6 -> 1.5806452 | J6: =F6/B6 -> 18452.854 | K6: =G6/B6 -> 5825.5829
A7: F. Müller | B7: =COUNTIF(clean_data!T:T,sales!A7) -> 51 | C7: =_xlfn.MINIFS(clean_data!F:F,clean_data!T:T,sales!A7) -> 44948 | D7: =_xlfn.MAXIFS(clean_data!F:F,clean_data!T:T,sales!A7) -> 45912 | E7: =DATEDIF(C7,D7,"m") -> 31 | F7: =SUMIF(clean_data!T:T,sales!A7,clean_data!AM:AM) -> 812637.17 | G7: =SUMIF(clean_data!T:T,sales!A7,clean_data!AN:AN) -> 251733.01 | H7: =AVERAGEIF(Table1[Salesperson],sales!A7,clean_data!AA:AA) -> 0.11254902 | I7: =B7/E7 -> 1.6451613 | J7: =F7/B7 -> 15934.062 | K7: =G7/B7 -> 4935.9414
A8: M. Rossi | B8: =COUNTIF(clean_data!T:T,sales!A8) -> 48 | C8: =_xlfn.MINIFS(clean_data!F:F,clean_data!T:T,sales!A8) -> 44938 | D8: =_xlfn.MAXIFS(clean_data!F:F,clean_data!T:T,sales!A8) -> 45902 | E8: =DATEDIF(C8,D8,"m") -> 31 | F8: =SUMIF(clean_data!T:T,sales!A8,clean_data!AM:AM) -> 966298.99 | G8: =SUMIF(clean_data!T:T,sales!A8,clean_data!AN:AN) -> 302657.06 | H8: =AVERAGEIF(Table1[Salesperson],sales!A8,clean_data!AA:AA) -> 0.11735417 | I8: =B8/E8 -> 1.5483871 | J8: =F8/B8 -> 20131.229 | K8: =G8/B8 -> 6305.3554
A9: O. Wang | B9: =COUNTIF(clean_data!T:T,sales!A9) -> 37 | C9: =_xlfn.MINIFS(clean_data!F:F,clean_data!T:T,sales!A9) -> 44941 | D9: =_xlfn.MAXIFS(clean_data!F:F,clean_data!T:T,sales!A9) -> 45910 | E9: =DATEDIF(C9,D9,"m") -> 31 | F9: =SUMIF(clean_data!T:T,sales!A9,clean_data!AM:AM) -> 647724.9 | G9: =SUMIF(clean_data!T:T,sales!A9,clean_data!AN:AN) -> 185219.44 | H9: =AVERAGEIF(Table1[Salesperson],sales!A9,clean_data!AA:AA) -> 0.12578378 | I9: =B9/E9 -> 1.1935484 | J9: =F9/B9 -> 17506.078 | K9: =G9/B9 -> 5005.9307
A10: H. Kim | B10: =COUNTIF(clean_data!T:T,sales!A10) -> 47 | C10: =_xlfn.MINIFS(clean_data!F:F,clean_data!T:T,sales!A10) -> 44939 | D10: =_xlfn.MAXIFS(clean_data!F:F,clean_data!T:T,sales!A10) -> 45855 | E10: =DATEDIF(C10,D10,"m") -> 30 | F10: =SUMIF(clean_data!T:T,sales!A10,clean_data!AM:AM) -> 727151.52 | G10: =SUMIF(clean_data!T:T,sales!A10,clean_data!AN:AN) -> 144057.31 | H10: =AVERAGEIF(Table1[Salesperson],sales!A10,clean_data!AA:AA) -> 0.11246809 | I10: =B10/E10 -> 1.5666667 | J10: =F10/B10 -> 15471.309 | K10: =G10/B10 -> 3065.0491
A11: C. Otieno | B11: =COUNTIF(clean_data!T:T,sales!A11) -> 37 | C11: =_xlfn.MINIFS(clean_data!F:F,clean_data!T:T,sales!A11) -> 44980 | D11: =_xlfn.MAXIFS(clean_data!F:F,clean_data!T:T,sales!A11) -> 45908 | E11: =DATEDIF(C11,D11,"m") -> 30 | F11: =SUMIF(clean_data!T:T,sales!A11,clean_data!AM:AM) -> 685111.86 | G11: =SUMIF(clean_data!T:T,sales!A11,clean_data!AN:AN) -> 225695.02 | H11: =AVERAGEIF(Table1[Salesperson],sales!A11,clean_data!AA:AA) -> 0.13578378 | I11: =B11/E11 -> 1.2333333 | J11: =F11/B11 -> 18516.537 | K11: =G11/B11 -> 6099.8654
A12: J. Njeri | B12: =COUNTIF(clean_data!T:T,sales!A12) -> 50 | C12: =_xlfn.MINIFS(clean_data!F:F,clean_data!T:T,sales!A12) -> 45012 | D12: =_xlfn.MAXIFS(clean_data!F:F,clean_data!T:T,sales!A12) -> 45911 | E12: =DATEDIF(C12,D12,"m") -> 29 | F12: =SUMIF(clean_data!T:T,sales!A12,clean_data!AM:AM) -> 802384.66 | G12: =SUMIF(clean_data!T:T,sales!A12,clean_data!AN:AN) -> 273113.11 | H12: =AVERAGEIF(Table1[Salesperson],sales!A12,clean_data!AA:AA) -> 0.11814 | I12: =B12/E12 -> 1.7241379 | J12: =F12/B12 -> 16047.693 | K12: =G12/B12 -> 5462.2622
A13: K. Singh | B13: =COUNTIF(clean_data!T:T,sales!A13) -> 44 | C13: =_xlfn.MINIFS(clean_data!F:F,clean_data!T:T,sales!A13) -> 44972 | D13: =_xlfn.MAXIFS(clean_data!F:F,clean_data!T:T,sales!A13) -> 45901 | E13: =DATEDIF(C13,D13,"m") -> 30 | F13: =SUMIF(clean_data!T:T,sales!A13,clean_data!AM:AM) -> 883348.13 | G13: =SUMIF(clean_data!T:T,sales!A13,clean_data!AN:AN) -> 278762.27 | H13: =AVERAGEIF(Table1[Salesperson],sales!A13,clean_data!AA:AA) -> 0.14031818 | I13: =B13/E13 -> 1.4666667 | J13: =F13/B13 -> 20076.094 | K13: =G13/B13 -> 6335.5061
... A16: N. Brown | B16: =COUNTIF(clean_data!T:T,sales!A16) -> 32 | C16: =_xlfn.MINIFS(clean_data!F:F,clean_data!T:T,sales!A16) -> 44953 | D16: =_xlfn.MAXIFS(clean_data!F:F,clean_data!T:T,sales!A16) -> 45914 | E16: =DATEDIF(C16,D16,"m") -> 31 | F16: =SUMIF(clean_data!T:T,sales!A16,clean_data!AM:AM) -> 388325.14 | G16: =SUMIF(clean_data!T:T,sales!A16,clean_data!AN:AN) -> 110646.46 | H16: =AVERAGEIF(Table1[Salesperson],sales!A16,clean_data!AA:AA) -> 0.09959375 | I16: =B16/E16 -> 1.0322581 | J16: =F16/B16 -> 12135.161 | K16: =G16/B16 -> 3457.7018
A19: Row Labels | B19: Revenue
A20: 1 | B20: 701241.31
A21: 2 | B21: 962551.41
A22: 3 | B22: 798978.3
A23: 4 | B23: 947246.58
A24: 5 | B24: 1262173.9
A25: 6 | B25: 1252428.2
A26: 7 | B26: 1313062.3
A27: 8 | B27: 1089608.8
A28: 9 | B28: 661159.43
A29: 10 | B29: 658776.06
A30: 11 | B30: 543953.69
A31: 12 | B31: 734787.61
A32: Grand Total | B32: 10925968

Sheet Quantiles
A1: Quartile | B1: value
A2: Low | B2: =_xlfn.PERCENTILE.INC(clean_data!Y:Y,0.33) -> 816.0801
A3: Medium | B3: =_xlfn.PERCENTILE.INC(clean_data!Y:Y,0.67) -> 1640.0575
A4: High

Sheet Cohort_analysis
A3: Sum of gross_revenue | B3: cohorts
A4: Row Labels | B4: 0 | C4: 1 | D4: 2 | E4: 3 | F4: 4 | G4: 5 | H4: 6 | I4: 7 | J4: 8 | K4: 9 | L4: 10 | M4: 11 | N4: 12 | O4: 13 | P4: 14 | Q4: 15 | R4: 16 | S4: 17 | T4: 18 | U4: 19 | V4: 20 | W4: 21 | X4: 22 | Y4: 23 | Z4: 24 | AA4: 25 | AB4: 26 | AC4: 27 | AD4: 28 | AE4: 29 | AF4: 30 | AG4: 31 | AH4: 32 | AI4: Grand Total
A5: Brazil | B5: 26695.838 | C5: 24523.007 | D5: 12248.676 | E5: 27194.152 | F5: 46991.747 | G5: 93430.735 | H5: 37330.003 | I5: 7071.6331 | J5: 16213.633 | K5: 24161.263 | L5: 61471.697 | M5: 8567.3925 | N5: 39239.198 | O5: 110.1492 | P5: 57491.063 | Q5: 9469.7678 | S5: 52596.047 | T5: 41358.42 | U5: 85419.018 | W5: 11939.431 | Y5: 22987.328 | Z5: 70563.592 | AA5: 15158.393 | AB5: 70019.054 | AC5: 67158.245 | AE5: 38096.184 | AF5: 45754.744 | AG5: 24172.045 | AI5: 1037432.5
A6: Canada | B6: 4141.76 | C6: 26150.364 | D6: 17453.344 | E6: 15618.845 | G6: 46226.12 | H6: 29536.716 | I6: 52625.804 | J6: 15530.93 | K6: 27756.432 | M6: 14466.951 | N6: 19139.594 | O6: 9774.3888 | P6: 21931.504 | R6: 17930.495 | S6: 55516.604 | T6: 79082.507 | U6: 7466.3064 | V6: 64160.245 | X6: 60697.471 | Y6: 20713.04 | AA6: 8128.5187 | AC6: 7901.5042 | AD6: 76122.593 | AE6: 5335.5655 | AF6: 141645.57 | AG6: 24972.288 | AH6: 12597.522 | AI6: 882622.98
A7: China | B7: 11406.96 | C7: 24306.483 | E7: 51137.289 | F7: 27108.715 | H7: 55186.877 | I7: 8909.8587 | J7: 72072.389 | K7: 4402.1165 | M7: 23668.56 | N7: 19542.975 | O7: 105288.56 | P7: 14197.064 | R7: 70180.56 | S7: 50774.407 | U7: 8934.8278 | V7: 60223.534 | W7: 20974.101 | X7: 4071.8 | Y7: 80623.678 | Z7: 52780.07 | AB7: 9378.6258 | AD7: 9684.8756 | AE7: 70923.21 | AF7: 34592.244 | AG7: 4420.5962 | AI7: 894790.38
A8: France | B8: 9847.2359 | C8: 39546.775 | D8: 9022.35 | E8: 31788.702 | G8: 18211.877 | H8: 52945.156 | I8: 36549.429 | J8: 14877.464 | K8: 5159.7894 | L8: 22983.346 | M8: 28412.1 | N8: 36467.166 | O8: 13450.74 | P8: 61324.276 | Q8: 24321.57 | R8: 19313.865 | S8: 7399.4832 | T8: 20507.941 | U8: 9189.1635 | W8: 66499.005 | X8: 48264.828 | Y8: 25948.415 | Z8: 20050.102 | AA8: 12040.644 | AB8: 21725.844 | AC8: 11482.481 | AD8: 13839.265 | AE8: 8366.02 | AG8: 68199.913 | AI8: 757734.94
A9: Germany | B9: 99559.246 | C9: 63596.315 | D9: 104633.05 | F9: 23154.287 | G9: 14114.069 | I9: 215.1984 | L9: 64606.506 | M9: 25014.766 | N9: 16328.076 | O9: 33660.622 | P9: 47953.246 | Q9: 33968.99 | R9: 87491.59 | U9: 47066.844 | W9: 12955.825 | X9: 5538.3298 | Y9: 73330.964 | Z9: 30546.068 | AA9: 618.1998 | AB9: 16328.359 | AC9: 5734.3457 | AD9: 56391.305 | AE9: 10441.908 | AF9: 56176.778 | AI9: 929424.89
A10: India | B10: 48804.159 | C10: 6631.6443 | D10: 32506.559 | E10: 249678.14 | F10: 4577.148 | G10: 12462.651 | I10: 49929.55 | J10: 25897.348 | K10: 48296.266 | L10: 35984.637 | M10: 33792.866 | N10: 24305.883 | O10: 12668.507 | Q10: 35554.1 | R10: 31513.423 | S10: 30229.995 | T10: 43785.688 | U10: 20028.787 | V10: 599.532 | W10: 80963.246 | X10: 51589.538 | Y10: 33308.55 | Z10: 7120.6486 | AA10: 24075.09 | AB10: 4856.3573 | AC10: 62421.225 | AD10: 39717.144 | AF10: 11006.648 | AG10: 29627.32 | AI10: 1091932.6
A11: Japan | B11: 31024.839 | C11: 21196.913 | D11: 9062.3469 | E11: 4603.0824 | F11: 32142.114 | H11: 31130.742 | I11: 14527.748 | J11: 27905.896 | K11: 65358.034 | L11: 26621.873 | M11: 15253.07 | P11: 14287.896 | Q11: 68665.574 | R11: 23449.834 | S11: 82602.551 | T11: 50582.706 | U11: 29808.425 | W11: 18641.222 | X11: 23394.92 | Y11: 266.17822 | Z11: 49494.319 | AA11: 20606.464 | AB11: 63856.507 | AC11: 11984.891 | AD11: 43398.362 | AF11: 74882.386 | AI11: 854748.89
A12: Kenya | B12: 47962.718 | C12: 9922.4369 | D12: 67069.607 | E12: 18037.279 | F12: 3799.8031 | G12: 19581.87 | H12: 17735.678 | I12: 1030.7574 | J12: 27249 | K12: 11015.51 | M12: 16061.973 | N12: 66852.129 | O12: 4866.3288 | P12: 8326.6853 | Q12: 29230.059 | R12: 84556.747 | S12: 101032.66 | T12: 27605.926 | U12: 52863.981 | W12: 54242.046 | X12: 119943.7 | Z12: 68469.848 | AB12: 31401.433 | AC12: 4569.8508 | AE12: 17867.219 | AF12: 1654.8966 | AG12: 22570.034 | AI12: 935520.18
A13: Nigeria | B13: 5422.2876 | D13: 32280.325 | E13: 20656.558 | F13: 22882.675 | G13: 116202.88 | H13: 3021.5016 | I13: 24833.098 | J13: 10786.321 | M13: 27158.894 | O13: 28041.025 | P13: 32335.218 | Q13: 51003.081 | R13: 46428.36 | S13: 2719.8567 | U13: 2879.9836 | V13: 55700.646 | W13: 44369.071 | X13: 12967.959 | Z13: 2146.5581 | AA13: 25958.851 | AB13: 48310.143 | AC13: 40139.875 | AD13: 11947.368 | AE13: 146296.57 | AF13: 17847.907 | AG13: 49501.66 | AI13: 881838.68
A14: South Africa | B14: 3116.21 | C14: 86597.081 | D14: 29618.551 | F14: 15187.141 | G14: 21572.591 | H14: 56993.802 | I14: 58520.37 | K14: 434.45248 | L14: 12954.358 | M14: 79406.785 | N14: 54214.972 | O14: 4826.5396 | Q14: 20171.633 | R14: 14032.851 | S14: 39907.476 | U14: 40303.832 | V14: 18061.204 | Z14: 6576.299 | AB14: 5565.3273 | AC14: 1886.9916 | AD14: 31556.188 | AE14: 88311.187 | AF14: 76636.156 | AH14: 13185.543 | AI14: 779637.54
A15: United Kingdom | B15: 27965.367 | C15: 4132.0325 | D15: 64680.119 | E15: 17884.688 | F15: 49706.427 | G15: 48616.566 | H15: 8763.285 | I15: 23038.616 | K15: 31613.31 | M15: 23195.018 | N15: 4229.4321 | O15: 33938.143 | P15: 13218.5 | Q15: 121707.26 | R15: 30151.675 | S15: 35167.745 | T15: 23687.524 | U15: 25249.613 | V15: 91431.438 | W15: 44605.989 | X15: 28827.107 | Y15: 30799.274 | Z15: 47052.461 | AB15: 117895.35 | AD15: 39263.703 | AE15: 77588.78 | AF15: 38415.603 | AG15: 8764.4066 | AI15: 1111589.4
A16: USA | B16: 47908.668 | C16: 51865.197 | E16: 15674.498 | F16: 23132.398 | G16: 71887.464 | H16: 32086.376 | I16: 25299.04 | J16: 20226.246 | M16: 12130.904 | N16: 24439.103 | O16: 59638.251 | P16: 83439.188 | R16: 53872.641 | T16: 71968.627 | U16: 63145.135 | W16: 16023.123 | Y16: 14568.782 | Z16: 2117.4835 | AA16: 9984.7161 | AB16: 2915.4541 | AC16: 35325.243 | AD16: 3644.3213 | AF16: 16609.091 | AG16: 10792.637 | AI16: 768694.59
A17: Grand Total | B17: 363855.29 | C17: 358468.25 | D17: 378574.93 | E17: 452273.23 | F17: 248682.46 | G17: 462306.83 | H17: 324730.14 | I17: 302551.1 | J17: 230759.23 | K17: 218197.17 | L17: 224622.42 | M17: 307129.28 | N17: 304758.53 | O17: 306263.26 | P17: 354504.64 | Q17: 394092.04 | R17: 478922.04 | S17: 457946.82 | T17: 358579.34 | U17: 392355.92 | V17: 290176.6 | W17: 371213.06 | X17: 355295.66 | Y17: 302546.21 | Z17: 356917.45 | AA17: 116570.88 | AB17: 392252.46 | AC17: 248604.65 | AD17: 325565.12 | AE17: 463226.64 | AF17: 515222.02 | AG17: 243020.9 | AH17: 25783.065 | AI17: 10925968

Sheet price_compliance
A1: Price Compliance — Share of Orders with Discount > 20%
A3: Region | B3: Total Orders | C3: Orders >20% | D3: Share >20% | F3: Salesperson | G3: Total Orders | H3: Orders >20% | I3: Share >20% | J3: Avg Discount
A4: Africa | B4: =COUNTIF(clean_data!$O:$O,$A4) -> 145 | C4: =COUNTIFS(clean_data!$O:$O,$A4,clean_data!$AA:$AA,">0.2") -> 22 | D4: =C4/B4 -> 0.15172414 | F4: A. Patel | G4: =COUNTIF(clean_data!$T:$T,$F4) -> 48 | H4: =COUNTIFS(clean_data!$T:$T,$F4,clean_data!$AA:$AA,">0.2") -> 10 | I4: =H4/G4 -> 0.20833333 | J4: =AVERAGEIF(clean_data!$T:$T,$F4,clean_data!$AA:$AA) -> 0.133875
A5: Americas | B5: =COUNTIF(clean_data!$O:$O,$A5) -> 157 | C5: =COUNTIFS(clean_data!$O:$O,$A5,clean_data!$AA:$AA,">0.2") -> 27 | D5: =C5/B5 -> 0.17197452 | F5: B. Chen | G5: =COUNTIF(clean_data!$T:$T,$F5) -> 48 | H5: =COUNTIFS(clean_data!$T:$T,$F5,clean_data!$AA:$AA,">0.2") -> 5 | I5: =H5/G5 -> 0.10416667 | J5: =AVERAGEIF(clean_data!$T:$T,$F5,clean_data!$AA:$AA) -> 0.109625
A6: Asia | B6: =COUNTIF(clean_data!$O:$O,$A6) -> 171 | C6: =COUNTIFS(clean_data!$O:$O,$A6,clean_data!$AA:$AA,">0.2") -> 24 | D6: =C6/B6 -> 0.14035088 | F6: C. Otieno | G6: =COUNTIF(clean_data!$T:$T,$F6) -> 37 | H6: =COUNTIFS(clean_data!$T:$T,$F6,clean_data!$AA:$AA,">0.2") -> 8 | I6: =H6/G6 -> 0.21621622 | J6: =AVERAGEIF(clean_data!$T:$T,$F6,clean_data!$AA:$AA) -> 0.13210811
A7: Europe | B7: =COUNTIF(clean_data!$O:$O,$A7) -> 159 | C7: =COUNTIFS(clean_data!$O:$O,$A7,clean_data!$AA:$AA,">0.2") -> 17 | D7: =C7/B7 -> 0.10691824 | F7: D. Smith | G7: =COUNTIF(clean_data!$T:$T,$F7) -> 39 | H7: =COUNTIFS(clean_data!$T:$T,$F7,clean_data!$AA:$AA,">0.2") -> 8 | I7: =H7/G7 -> 0.20512821 | J7: =AVERAGEIF(clean_data!$T:$T,$F7,clean_data!$AA:$AA) -> 0.12628205
F8: E. Garcia | G8: =COUNTIF(clean_data!$T:$T,$F8) -> 34 | H8: =COUNTIFS(clean_data!$T:$T,$F8,clean_data!$AA:$AA,">0.2") -> 3 | I8: =H8/G8 -> 0.088235294 | J8: =AVERAGEIF(clean_data!$T:$T,$F8,clean_data!$AA:$AA) -> 0.10520588
F9: F. Müller | G9: =COUNTIF(clean_data!$T:$T,$F9) -> 51 | H9: =COUNTIFS(clean_data!$T:$T,$F9,clean_data!$AA:$AA,">0.2") -> 4 | I9: =H9/G9 -> 0.078431373 | J9: =AVERAGEIF(clean_data!$T:$T,$F9,clean_data!$AA:$AA) -> 0.10013725
A10: Outlier orders (Discount > 20%), sorted by discount | F10: G. Dubois | G10: =COUNTIF(clean_data!$T:$T,$F10) -> 30 | H10: =COUNTIFS(clean_data!$T:$T,$F10,clean_data!$AA:$AA,">0.2") -> 3 | I10: =H10/G10 -> 0.1 | J10: =AVERAGEIF(clean_data!$T:$T,$F10,clean_data!$AA:$AA) -> 0.1172
A11: OrderID | B11: Region | C11: Salesperson | D11: Category | E11: Discount % | F11: H. Kim | G11: =COUNTIF(clean_data!$T:$T,$F11) -> 47 | H11: =COUNTIFS(clean_data!$T:$T,$F11,clean_data!$AA:$AA,">0.2") -> 4 | I11: =H11/G11 -> 0.085106383 | J11: =AVERAGEIF(clean_data!$T:$T,$F11,clean_data!$AA:$AA) -> 0.12865957
A12: {=_xlfn._xlws.SORT(_xlfn._xlws.FILTER(CHOOSE({1,2,3,4,5},clean_data!$B$2:$B$633,clean_data!$O$2:$O$633,clean_data!$T$2:$T$633,clean_data!$U$2:$U$633,clean_data!$AA$2:$AA$633),clean_data!$AA$2:$AA$633>0.2),5,-1)} -> 261081 | B12: Africa | C12: M. Rossi | D12: Accessories | E12: 0.565 | F12: I. Johnson | G12: =COUNTIF(clean_data!$T:$T,$F12) -> 38 | H12: =COUNTIFS(clean_data!$T:$T,$F12,clean_data!$AA:$AA,">0.2") -> 9 | I12: =H12/G12 -> 0.23684211 | J12: =AVERAGEIF(clean_data!$T:$T,$F12,clean_data!$AA:$AA) -> 0.13473684
A13: 368449 | B13: Asia | C13: C. Otieno | D13: Components | E13: 0.357 | F13: J. Njeri | G13: =COUNTIF(clean_data!$T:$T,$F13) -> 50 | H13: =COUNTIFS(clean_data!$T:$T,$F13,clean_data!$AA:$AA,">0.2") -> 6 | I13: =H13/G13 -> 0.12 | J13: =AVERAGEIF(clean_data!$T:$T,$F13,clean_data!$AA:$AA) -> 0.1172
A14: 779530 | B14: Americas | C14: L. Okafor | D14: Monitors | E14: 0.346 | F14: K. Singh | G14: =COUNTIF(clean_data!$T:$T,$F14) -> 44 | H14: =COUNTIFS(clean_data!$T:$T,$F14,clean_data!$AA:$AA,">0.2") -> 4 | I14: =H14/G14 -> 0.090909091 | J14: =AVERAGEIF(clean_data!$T:$T,$F14,clean_data!$AA:$AA) -> 0.11825
A15: 382272 | B15: Africa | C15: A. Patel | D15: Components | E15: 0.343 | F15: L. Okafor | G15: =COUNTIF(clean_data!$T:$T,$F15) -> 49 | H15: =COUNTIFS(clean_data!$T:$T,$F15,clean_data!$AA:$AA,">0.2") -> 9 | I15: =H15/G15 -> 0.18367347 | J15: =AVERAGEIF(clean_data!$T:$T,$F15,clean_data!$AA:$AA) -> 0.12789796
A16: 998320 | B16: Africa | C16: H. Kim | D16: Printers | E16: 0.318 | F16: M. Rossi | G16: =COUNTIF(clean_data!$T:$T,$F16) -> 48 | H16: =COUNTIFS(clean_data!$T:$T,$F16,clean_data!$AA:$AA,">0.2") -> 8 | I16: =H16/G16 -> 0.16666667 | J16: =AVERAGEIF(clean_data!$T:$T,$F16,clean_data!$AA:$AA) -> 0.12789583
A17: 685236 | B17: Asia | C17: H. Kim | D17: Networking | E17: 0.317 | F17: N. Brown | G17: =COUNTIF(clean_data!$T:$T,$F17) -> 32 | H17: =COUNTIFS(clean_data!$T:$T,$F17,clean_data!$AA:$AA,">0.2") -> 5 | I17: =H17/G17 -> 0.15625 | J17: =AVERAGEIF(clean_data!$T:$T,$F17,clean_data!$AA:$AA) -> 0.11159375
A18: 993481 | B18: Asia | C18: C. Otieno | D18: Phones | E18: 0.314 | F18: O. Wang | G18: =COUNTIF(clean_data!$T:$T,$F18) -> 37 | H18: =COUNTIFS(clean_data!$T:$T,$F18,clean_data!$AA:$AA,">0.2") -> 4 | I18: =H18/G18 -> 0.10810811 | J18: =AVERAGEIF(clean_data!$T:$T,$F18,clean_data!$AA:$AA) -> 0.12935135
A19: 825084 | B19: Africa | C19: A. Patel | D19: Monitors | E19: 0.299
A20: 260775 | B20: Asia | C20: O. Wang | D20: Monitors | E20: 0.295
A21: 473192 | B21: Africa | C21: J. Njeri | D21: Monitors | E21: 0.293
A22: 468501 | B22: Americas | C22: D. Smith | D22: Accessories | E22: 0.292
A23: 422918 | B23: Europe | C23: H. Kim | D23: Laptops | E23: 0.292
A24: 766015 | B24: Americas | C24: G. Dubois | D24: Networking | E24: 0.282
A25: 155337 | B25: Africa | C25: M. Rossi | D25: Components | E25: 0.278
A26: 343877 | B26: Asia | C26: K. Singh | D26: Monitors | E26: 0.272
A27: 944052 | B27: Asia | C27: L. Okafor | D27: Accessories | E27: 0.27
A28: 777623 | B28: Americas | C28: K. Singh | D28: Printers | E28: 0.266
A29: 613287 | B29: Africa | C29: C. Otieno | D29: Phones | E29: 0.265
A30: 544865 | B30: Americas | C30: D. Smith | D30: Laptops | E30: 0.263
... A101: 197852 | B101: Asia | C101: I. Johnson | D101: Networking | E101: 0.201

Sheet channelmix
A1: Sum of gross_revenue | B1: Column Labels
A2: Row Labels | B2: Direct | C2: Distributor | D2: Marketplace | E2: Online | F2: Retail | G2: Grand Total
A3: Africa | B3: 463083.86 | C3: 654956.14 | D3: 527467.87 | E3: 433406.34 | F3: 518082.19 | G3: 2596996.4
A4: Americas | B4: 751887.69 | C4: 568425.23 | D4: 375632.07 | E4: 689951.45 | F4: 302853.58 | G4: 2688750
A5: Asia | B5: 642428.79 | C5: 509418.81 | D5: 572954.82 | E5: 423527.82 | F5: 693141.68 | G5: 2841471.9
A6: Europe | B6: 860664.9 | C6: 318736.67 | D6: 569130.56 | E6: 585406.72 | F6: 464810.42 | G6: 2798749.3
A7: Grand Total | B7: 2718065.2 | C7: 2051536.9 | D7: 2045185.3 | E7: 2132292.3 | F7: 1978887.9 | G7: 10925968
A9: Canibalization
B10: Column Labels
B11: Africa | G11: Americas | L11: Asia | Q11: Europe | V11: Total Sum of gross_revenue | W11: Total Count of short_order_id | X11: Total Sum of lead_proxy | Y11: Total Sum of gross_profit | Z11: Total Average of Margin %
A12: Row Labels | B12: Sum of gross_revenue | C12: Count of short_order_id | D12: Sum of lead_proxy | E12: Sum of gross_profit | F12: Average of Margin % | G12: Sum of gross_revenue | H12: Count of short_order_id | I12: Sum of lead_proxy | J12: Sum of gross_profit | K12: Average of Margin % | L12: Sum of gross_revenue | M12: Count of short_order_id | N12: Sum of lead_proxy | O12: Sum of gross_profit | P12: Average of Margin % | Q12: Sum of gross_revenue | R12: Count of short_order_id | S12: Sum of lead_proxy | T12: Sum of gross_profit | U12: Average of Margin %
A13: Direct
A14: 2023 | B14: 98372.291 | C14: 8 | D14: 3 | E14: 25657.771 | F14: 0.13385606 | G14: 265177.69 | H14: 14 | I14: 5 | J14: 80137.204 | K14: 0.25888456 | L14: 160674.76 | M14: 10 | N14: 0 | O14: 62146.463 | P14: 0.32805746 | Q14: 434361.75 | R14: 25 | S14: 7 | T14: 148298.1 | U14: 0.24633328 | V14: 958586.5 | W14: 57 | X14: 15 | Y14: 316239.54 | Z14: 0.24796735
A15: 2024 | B15: 269534.38 | C15: 12 | D15: 8 | E15: 128819.41 | F15: 0.40033244 | G15: 347616.43 | H15: 16 | I15: 4 | J15: 130404.07 | K15: 0.28569302 | L15: 239302.24 | M15: 13 | N15: 4 | O15: 61479.803 | P15: 0.19281226 | Q15: 281598.94 | R15: 15 | S15: 2 | T15: 98843.823 | U15: 0.29484638 | V15: 1138052 | W15: 56 | X15: 18 | Y15: 419547.11 | Z15: 0.2911488
A16: 2025 | B16: 95177.188 | C16: 9 | D16: 1 | E16: 23293.008 | F16: 0.16357764 | G16: 139093.56 | H16: 9 | I16: 1 | J16: 48133.647 | K16: 0.25604519 | L16: 242451.78 | M16: 13 | N16: 2 | O16: 105591.21 | P16: 0.37346541 | Q16: 144704.21 | R16: 13 | S16: 2 | T16: 53603.738 | U16: 0.27731136 | V16: 621426.74 | W16: 44 | X16: 6 | Y16: 230621.61 | Z16: 0.2781069
A17: Distributor
A18: 2023 | B18: 169759.89 | C18: 9 | D18: 1 | E18: 50592.482 | F18: 0.14840768 | G18: 132332.44 | H18: 12 | I18: 5 | J18: 33572.268 | K18: 0.22690656 | L18: 113566.36 | M18: 11 | N18: 2 | O18: 40308.186 | P18: 0.24617934 | Q18: 132597.12 | R18: 7 | S18: 2 | T18: 68446.143 | U18: 0.38114222 | V18: 548255.81 | W18: 39 | X18: 10 | Y18: 192919.08 | Z18: 0.24191067
A19: 2024 | B19: 305224.18 | C19: 15 | D19: 3 | E19: 83429.054 | F19: 0.23671557 | G19: 254923.65 | H19: 12 | I19: 1 | J19: 78547.57 | K19: 0.22051652 | L19: 257287.55 | M19: 13 | N19: 5 | O19: 77982.242 | P19: 0.23199008 | Q19: 147615.36 | R19: 7 | S19: 1 | T19: 20254.768 | U19: 0.090269535 | V19: 965050.74 | W19: 47 | X19: 10 | Y19: 260213.63 | Z19: 0.20946148
A20: 2025 | B20: 179972.06 | C20: 9 | D20: 4 | E20: 74407.794 | F20: 0.22291456 | G20: 181169.15 | H20: 13 | I20: 2 | J20: 63178.846 | K20: 0.17786414 | L20: 138564.9 | M20: 12 | N20: 1 | O20: 32856.319 | P20: 0.15176666 | Q20: 38524.191 | R20: 5 | S20: 2 | T20: 16849.941 | U20: 0.34873416 | V20: 538230.3 | W20: 39 | X20: 9 | Y20: 187292.9 | Z20: 0.20213681
A21: Marketplace
A22: 2023 | B22: 229365.43 | C22: 14 | D22: 6 | E22: 93405.605 | F22: 0.33014818 | G22: 148966.17 | H22: 11 | I22: 1 | J22: 49271.601 | K22: 0.39924175 | L22: 285429.23 | M22: 14 | N22: 2 | O22: 59337.397 | P22: 0.1143105 | Q22: 142074.07 | R22: 7 | S22: 1 | T22: 27508.322 | U22: 0.15511477 | V22: 805834.9 | W22: 46 | X22: 10 | Y22: 229522.93 | Z22: 0.25434531
A23: 2024 | B23: 103752.2 | C23: 9 | D23: 3 | E23: 34282.374 | F23: 0.2548359 | G23: 140826.02 | H23: 10 | I23: 6 | J23: 19046.064 | K23: 0.078134932 | L23: 189993.47 | M23: 12 | N23: 1 | O23: 57559.53 | P23: 0.22759173 | Q23: 230048.08 | R23: 12 | S23: 4 | T23: 71466.704 | U23: 0.29389346 | V23: 664619.78 | W23: 43 | X23: 14 | Y23: 182354.67 | Z23: 0.21703941
A24: 2025 | B24: 194350.25 | C24: 10 | D24: 1 | E24: 37151.325 | F24: 0.16056048 | G24: 85839.872 | H24: 7 | I24: 0 | J24: 29069.942 | K24: 0.2721857 | L24: 97532.127 | M24: 9 | N24: 0 | O24: 27678.507 | P24: 0.23124289 | Q24: 197008.4 | R24: 12 | S24: 3 | T24: 12171.812 | U24: 21.25129 | V24: 574730.65 | W24: 38 | X24: 4 | Y24: 106071.59 | Z24: 6.8580939
A25: Online
A26: 2023 | B26: 47302.583 | C26: 9 | D26: 2 | E26: 19155.913 | F26: 0.30906122 | G26: 204132.73 | H26: 11 | I26: 1 | J26: 90309.371 | K26: 0.42404724 | L26: 87807.929 | M26: 6 | N26: 1 | O26: 29321.569 | P26: 0.37184688 | Q26: 88834.508 | R26: 6 | S26: 3 | T26: 27775.808 | U26: 0.058117222 | V26: 428077.75 | W26: 32 | X26: 7 | Y26: 166562.66 | Z26: 0.31330797
A27: 2024 | B27: 222051.79 | C27: 12 | D27: 1 | E27: 55100.02 | F27: 0.2295029 | G27: 222681.56 | H27: 11 | I27: 1 | J27: 83130.264 | K27: 0.23317171 | L27: 258545.66 | M27: 15 | N27: 1 | O27: 96164.778 | P27: 0.27655328 | Q27: 307763.14 | R27: 14 | S27: 3 | T27: 112598.56 | U27: 0.33848892 | V27: 1011042.1 | W27: 52 | X27: 6 | Y27: 346993.62 | Z27: 0.27319361
A28: 2025 | B28: 164051.96 | C28: 4 | D28: 1 | E28: 71198.014 | F28: 0.35700647 | G28: 263137.16 | H28: 8 | I28: 2 | J28: 88504.21 | K28: 0.31711666 | L28: 77174.233 | M28: 7 | N28: 4 | O28: 27573.163 | P28: 0.35109934 | Q28: 188809.08 | R28: 8 | S28: 2 | T28: 59692.8 | U28: 0.21883942 | V28: 693172.44 | W28: 27 | X28: 9 | Y28: 246968.19 | Z28: 0.3027174
A29: Retail
A30: 2023 | B30: 322312.33 | C30: 14 | D30: 4 | E30: 67212.539 | F30: 4.1494266 | G30: 164310.5 | H30: 10 | I30: 2 | J30: 25692.813 | K30: 0.11139602 | L30: 341951.99 | M30: 19 | N30: 3 | O30: 78496.214 | P30: 0.12043681 | Q30: 117755.86 | R30: 9 | S30: 0 | T30: 34526.906 | U30: 0.25727434 | V30: 946330.68 | W30: 52 | X30: 9 | Y30: 205928.47 | Z30: 1.2271096
A31: 2024 | B31: 116921.42 | C31: 7 | D31: 1 | E31: 36881.696 | F31: 0.28600775 | G31: 93243.432 | H31: 8 | I31: 1 | J31: 35288.402 | K31: 0.35753272 | L31: 221621.69 | M31: 11 | N31: 2 | O31: 39902.851 | P31: 0.18358636 | Q31: 255178.91 | R31: 14 | S31: 3 | T31: 89114.369 | U31: 2.0397829 | V31: 686965.45 | W31: 40 | X31: 7 | Y31: 201187.32 | Z31: 0.88596815
A32: 2025 | B32: 78848.445 | C32: 4 | D32: 0 | E32: 36437.405 | F32: 0.39377135 | G32: 45299.644 | H32: 5 | I32: 1 | J32: 8054.4939 | K32: 0.13686448 | L32: 129567.99 | M32: 6 | N32: 2 | O32: 34859.494 | P32: 0.18032738 | Q32: 91875.654 | R32: 5 | S32: 1 | T32: 26445.204 | U32: 0.28009961 | V32: 345591.74 | W32: 20 | X32: 4 | Y32: 105796.6 | Z32: 0.23709351
A33: Grand Total | B33: 2596996.4 | C33: 145 | D33: 39 | E33: 837024.41 | F33: 0.63030067 | G33: 2688750 | H33: 157 | I33: 33 | J33: 862340.77 | K33: 0.25276678 | L33: 2841471.9 | M33: 171 | N33: 30 | O33: 831257.73 | P33: 0.22705644 | Q33: 2798749.3 | R33: 159 | S33: 36 | T33: 867596.99 | U33: 1.9998039 | V33: 10925968 | W33: 632 | X33: 138 | Y33: 3398219.9 | Z33: 0.77195167
A38: Sum of gross_profit | B38: Column Labels
A39: Row Labels | B39: Direct | C39: Distributor | D39: Marketplace | E39: Online | F39: Retail
A40: Africa | B40: 177770.19 | C40: 208429.33 | D40: 164839.3 | E40: 145453.95 | F40: 140531.64
A41: Americas | B41: 258674.93 | C41: 175298.68 | D41: 97387.608 | E41: 261943.84 | F41: 69035.709
A42: Asia | B42: 229217.48 | C42: 151146.75 | D42: 144575.43 | E42: 153059.51 | F42: 153258.56
A43: Europe | B43: 300745.66 | C43: 105550.85 | D43: 111146.84 | E43: 200067.16 | F43: 150086.48
A45: Row Labels | B45: Sum of gross_revenue
A46: CMP-3938 | B46: 84136.12
A47: CMP-8851 | B47: 139277.83
A48: LAP-3904 | B48: 82514.712
A49: LAP-8910 | B49: 102122.94
A50: MON-2266 | B50: 87404.93
A51: MON-6699 | B51: 85637.74
A52: MON-6962 | B52: 92715.25
A53: NET-2365 | B53: 109244
A54: NET-5523 | B54: 79548.756
A55: NET-5987 | B55: 82141.34

Sheet Dashboard
B1: SALES DASHBOARD
A3: GROSS REVENUE | E3: GROSS_PROFIT | I3: MARGIN % | M3: AVG_ORDER_VALUE | Q3: ON_TIME %
A4: =GETPIVOTDATA("Sum of gross_revenue",channelmix!$A$10) -> 10925968 | E4: =GETPIVOTDATA("Sum of gross_profit",channelmix!$A$10) -> 3398219.9 | I4: =GETPIVOTDATA("Average of Margin %",channelmix!$A$10) -> 0.77195167 | M4: =IF(GETPIVOTDATA("Count of short_order_id",channelmix!$A$10)=0,0,A4/GETPIVOTDATA("Count of short_order_id",channelmix!$A$10)) -> 17287.923 | Q4: =IF(GETPIVOTDATA("Count of short_order_id",channelmix!$A$10)=0,0,GETPIVOTDATA("Sum of lead_proxy",channelmix!$A$10)/GETPIVOTDATA("Count of short_order_id",channelmix!$A$10)) -> 0.21835443

Sheet ABC_analysis
A1: ProductCategory | B1: SKU | C1: SKU Revenue | D1: Category Total | E1: Cumulative Revenue | F1: Cumulative % | G1: ABC Class | I1: ABC Summary — SKU count by class
A2: Accessories | B2: ACC-6626 | C2: =SUMIFS(clean_data!$AM:$AM,clean_data!$U:$U,$A2,clean_data!$V:$V,$B2) -> 79082.507 | D2: =SUMIF(clean_data!$U:$U,$A2,clean_data!$AM:$AM) -> 1331102.9 | E2: =C2 -> 79082.507 | F2: =E2/D2 -> 0.059411263 | G2: =IF(F2<=0.8,"A",IF(F2<=0.95,"B","C")) -> A | I2: ProductCategory | J2: A | K2: B | L2: C | M2: Total
A3: Accessories | B3: ACC-2988 | C3: =SUMIFS(clean_data!$AM:$AM,clean_data!$U:$U,$A3,clean_data!$V:$V,$B3) -> 53034.364 | D3: =SUMIF(clean_data!$U:$U,$A3,clean_data!$AM:$AM) -> 1331102.9 | E3: =IF(A3=A2,E2+C3,C3) -> 132116.87 | F3: =E3/D3 -> 0.099253684 | G3: =IF(F3<=0.8,"A",IF(F3<=0.95,"B","C")) -> A | I3: Accessories | J3: =COUNTIFS($A:$A,$I3,$G:$G,"A") -> 43 | K3: =COUNTIFS($A:$A,$I3,$G:$G,"B") -> 22 | L3: =COUNTIFS($A:$A,$I3,$G:$G,"C") -> 23 | M3: =SUM(J3:L3) -> 88
A4: Accessories | B4: ACC-9283 | C4: =SUMIFS(clean_data!$AM:$AM,clean_data!$U:$U,$A4,clean_data!$V:$V,$B4) -> 46450.26 | D4: =SUMIF(clean_data!$U:$U,$A4,clean_data!$AM:$AM) -> 1331102.9 | E4: =IF(A4=A3,E3+C4,C4) -> 178567.13 | F4: =E4/D4 -> 0.13414975 | G4: =IF(F4<=0.8,"A",IF(F4<=0.95,"B","C")) -> A | I4: Components | J4: =COUNTIFS($A:$A,$I4,$G:$G,"A") -> 39 | K4: =COUNTIFS($A:$A,$I4,$G:$G,"B") -> 25 | L4: =COUNTIFS($A:$A,$I4,$G:$G,"C") -> 26 | M4: =SUM(J4:L4) -> 90
A5: Accessories | B5: ACC-9533 | C5: =SUMIFS(clean_data!$AM:$AM,clean_data!$U:$U,$A5,clean_data!$V:$V,$B5) -> 43084.872 | D5: =SUMIF(clean_data!$U:$U,$A5,clean_data!$AM:$AM) -> 1331102.9 | E5: =IF(A5=A4,E4+C5,C5) -> 221652 | F5: =E5/D5 -> 0.16651755 | G5: =IF(F5<=0.8,"A",IF(F5<=0.95,"B","C")) -> A | I5: Laptops | J5: =COUNTIFS($A:$A,$I5,$G:$G,"A") -> 38 | K5: =COUNTIFS($A:$A,$I5,$G:$G,"B") -> 22 | L5: =COUNTIFS($A:$A,$I5,$G:$G,"C") -> 21 | M5: =SUM(J5:L5) -> 81
A6: Accessories | B6: ACC-8098 | C6: =SUMIFS(clean_data!$AM:$AM,clean_data!$U:$U,$A6,clean_data!$V:$V,$B6) -> 38096.184 | D6: =SUMIF(clean_data!$U:$U,$A6,clean_data!$AM:$AM) -> 1331102.9 | E6: =IF(A6=A5,E5+C6,C6) -> 259748.19 | F6: =E6/D6 -> 0.19513756 | G6: =IF(F6<=0.8,"A",IF(F6<=0.95,"B","C")) -> A | I6: Monitors | J6: =COUNTIFS($A:$A,$I6,$G:$G,"A") -> 40 | K6: =COUNTIFS($A:$A,$I6,$G:$G,"B") -> 26 | L6: =COUNTIFS($A:$A,$I6,$G:$G,"C") -> 28 | M6: =SUM(J6:L6) -> 94
A7: Accessories | B7: ACC-4490 | C7: =SUMIFS(clean_data!$AM:$AM,clean_data!$U:$U,$A7,clean_data!$V:$V,$B7) -> 35396.278 | D7: =SUMIF(clean_data!$U:$U,$A7,clean_data!$AM:$AM) -> 1331102.9 | E7: =IF(A7=A6,E6+C7,C7) -> 295144.47 | F7: =E7/D7 -> 0.22172926 | G7: =IF(F7<=0.8,"A",IF(F7<=0.95,"B","C")) -> A | I7: Networking | J7: =COUNTIFS($A:$A,$I7,$G:$G,"A") -> 36 | K7: =COUNTIFS($A:$A,$I7,$G:$G,"B") -> 23 | L7: =COUNTIFS($A:$A,$I7,$G:$G,"C") -> 27 | M7: =SUM(J7:L7) -> 86
A8: Accessories | B8: ACC-7838 | C8: =SUMIFS(clean_data!$AM:$AM,clean_data!$U:$U,$A8,clean_data!$V:$V,$B8) -> 35167.745 | D8: =SUMIF(clean_data!$U:$U,$A8,clean_data!$AM:$AM) -> 1331102.9 | E8: =IF(A8=A7,E7+C8,C8) -> 330312.21 | F8: =E8/D8 -> 0.24814926 | G8: =IF(F8<=0.8,"A",IF(F8<=0.95,"B","C")) -> A | I8: Phones | J8: =COUNTIFS($A:$A,$I8,$G:$G,"A") -> 40 | K8: =COUNTIFS($A:$A,$I8,$G:$G,"B") -> 23 | L8: =COUNTIFS($A:$A,$I8,$G:$G,"C") -> 25 | M8: =SUM(J8:L8) -> 88
A9: Accessories | B9: ACC-5177 | C9: =SUMIFS(clean_data!$AM:$AM,clean_data!$U:$U,$A9,clean_data!$V:$V,$B9) -> 34139.16 | D9: =SUMIF(clean_data!$U:$U,$A9,clean_data!$AM:$AM) -> 1331102.9 | E9: =IF(A9=A8,E8+C9,C9) -> 364451.37 | F9: =E9/D9 -> 0.27379653 | G9: =IF(F9<=0.8,"A",IF(F9<=0.95,"B","C")) -> A | I9: Printers | J9: =COUNTIFS($A:$A,$I9,$G:$G,"A") -> 48 | K9: =COUNTIFS($A:$A,$I9,$G:$G,"B") -> 27 | L9: =COUNTIFS($A:$A,$I9,$G:$G,"C") -> 28 | M9: =SUM(J9:L9) -> 103
A10: Accessories | B10: ACC-9162 | C10: =SUMIFS(clean_data!$AM:$AM,clean_data!$U:$U,$A10,clean_data!$V:$V,$B10) -> 33062.236 | D10: =SUMIF(clean_data!$U:$U,$A10,clean_data!$AM:$AM) -> 1331102.9 | E10: =IF(A10=A9,E9+C10,C10) -> 397513.61 | F10: =E10/D10 -> 0.29863476 | G10: =IF(F10<=0.8,"A",IF(F10<=0.95,"B","C")) -> A | I10: Total | J10: =SUM(J3:J9) -> 284 | K10: =SUM(K3:K9) -> 168 | L10: =SUM(L3:L9) -> 178 | M10: =SUM(M3:M9) -> 630
A11: Accessories | B11: ACC-7078 | C11: =SUMIFS(clean_data!$AM:$AM,clean_data!$U:$U,$A11,clean_data!$V:$V,$B11) -> 32086.376 | D11: =SUMIF(clean_data!$U:$U,$A11,clean_data!$AM:$AM) -> 1331102.9 | E11: =IF(A11=A10,E10+C11,C11) -> 429599.98 | F11: =E11/D11 -> 0.32273986 | G11: =IF(F11<=0.8,"A",IF(F11<=0.95,"B","C")) -> A
A12: Accessories | B12: ACC-1375 | C12: =SUMIFS(clean_data!$AM:$AM,clean_data!$U:$U,$A12,clean_data!$V:$V,$B12) -> 31513.085 | D12: =SUMIF(clean_data!$U:$U,$A12,clean_data!$AM:$AM) -> 1331102.9 | E12: =IF(A12=A11,E11+C12,C12) -> 461113.07 | F12: =E12/D12 -> 0.34641428 | G12: =IF(F12<=0.8,"A",IF(F12<=0.95,"B","C")) -> A
A13: Accessories | B13: ACC-1659 | C13: =SUMIFS(clean_data!$AM:$AM,clean_data!$U:$U,$A13,clean_data!$V:$V,$B13) -> 28386.016 | D13: =SUMIF(clean_data!$U:$U,$A13,clean_data!$AM:$AM) -> 1331102.9 | E13: =IF(A13=A12,E12+C13,C13) -> 489499.08 | F13: =E13/D13 -> 0.36773946 | G13: =IF(F13<=0.8,"A",IF(F13<=0.95,"B","C")) -> A
A14: Accessories | B14: ACC-6223 | C14: =SUMIFS(clean_data!$AM:$AM,clean_data!$U:$U,$A14,clean_data!$V:$V,$B14) -> 26765.04 | D14: =SUMIF(clean_data!$U:$U,$A14,clean_data!$AM:$AM) -> 1331102.9 | E14: =IF(A14=A13,E13+C14,C14) -> 516264.12 | F14: =E14/D14 -> 0.38784688 | G14: =IF(F14<=0.8,"A",IF(F14<=0.95,"B","C")) -> A
A15: Accessories | B15: ACC-4631 | C15: =SUMIFS(clean_data!$AM:$AM,clean_data!$U:$U,$A15,clean_data!$V:$V,$B15) -> 26759.288 | D15: =SUMIF(clean_data!$U:$U,$A15,clean_data!$AM:$AM) -> 1331102.9 | E15: =IF(A15=A14,E14+C15,C15) -> 543023.41 | F15: =E15/D15 -> 0.40794997 | G15: =IF(F15<=0.8,"A",IF(F15<=0.95,"B","C")) -> A
A16: Accessories | B16: ACC-5334 | C16: =SUMIFS(clean_data!$AM:$AM,clean_data!$U:$U,$A16,clean_data!$V:$V,$B16) -> 26552.603 | D16: =SUMIF(clean_data!$U:$U,$A16,clean_data!$AM:$AM) -> 1331102.9 | E16: =IF(A16=A15,E15+C16,C16) -> 569576.01 | F16: =E16/D16 -> 0.42789779 | G16: =IF(F16<=0.8,"A",IF(F16<=0.95,"B","C")) -> A
A17: Accessories | B17: ACC-6594 | C17: =SUMIFS(clean_data!$AM:$AM,clean_data!$U:$U,$A17,clean_data!$V:$V,$B17) -> 24278.849 | D17: =SUMIF(clean_data!$U:$U,$A17,clean_data!$AM:$AM) -> 1331102.9 | E17: =IF(A17=A16,E16+C17,C17) -> 593854.86 | F17: =E17/D17 -> 0.44613744 | G17: =IF(F17<=0.8,"A",IF(F17<=0.95,"B","C")) -> A
A18: Accessories | B18: ACC-9644 | C18: =SUMIFS(clean_data!$AM:$AM,clean_data!$U:$U,$A18,clean_data!$V:$V,$B18) -> 23668.56 | D18: =SUMIF(clean_data!$U:$U,$A18,clean_data!$AM:$AM) -> 1331102.9 | E18: =IF(A18=A17,E17+C18,C18) -> 617523.42 | F18: =E18/D18 -> 0.46391861 | G18: =IF(F18<=0.8,"A",IF(F18<=0.95,"B","C")) -> A
A19: Accessories | B19: ACC-8557 | C19: =SUMIFS(clean_data!$AM:$AM,clean_data!$U:$U,$A19,clean_data!$V:$V,$B19) -> 23375.594 | D19: =SUMIF(clean_data!$U:$U,$A19,clean_data!$AM:$AM) -> 1331102.9 | E19: =IF(A19=A18,E18+C19,C19) -> 640899.02 | F19: =E19/D19 -> 0.48147968 | G19: =IF(F19<=0.8,"A",IF(F19<=0.95,"B","C")) -> A
A20: Accessories | B20: ACC-3103 | C20: =SUMIFS(clean_data!$AM:$AM,clean_data!$U:$U,$A20,clean_data!$V:$V,$B20) -> 23195.018 | D20: =SUMIF(clean_data!$U:$U,$A20,clean_data!$AM:$AM) -> 1331102.9 | E20: =IF(A20=A19,E19+C20,C20) -> 664094.04 | F20: =E20/D20 -> 0.49890509 | G20: =IF(F20<=0.8,"A",IF(F20<=0.95,"B","C")) -> A
A21: Accessories | B21: ACC-1731 | C21: =SUMIFS(clean_data!$AM:$AM,clean_data!$U:$U,$A21,clean_data!$V:$V,$B21) -> 22620.86 | D21: =SUMIF(clean_data!$U:$U,$A21,clean_data!$AM:$AM) -> 1331102.9 | E21: =IF(A21=A20,E20+C21,C21) -> 686714.9 | F21: =E21/D21 -> 0.51589916 | G21: =IF(F21<=0.8,"A",IF(F21<=0.95,"B","C")) -> A
A22: Accessories | B22: ACC-3721 | C22: =SUMIFS(clean_data!$AM:$AM,clean_data!$U:$U,$A22,clean_data!$V:$V,$B22) -> 22526.66 | D22: =SUMIF(clean_data!$U:$U,$A22,clean_data!$AM:$AM) -> 1331102.9 | E22: =IF(A22=A21,E21+C22,C22) -> 709241.56 | F22: =E22/D22 -> 0.53282247 | G22: =IF(F22<=0.8,"A",IF(F22<=0.95,"B","C")) -> A
... A631: Printers | B631: PRN-6276 | C631: =SUMIFS(clean_data!$AM:$AM,clean_data!$U:$U,$A631,clean_data!$V:$V,$B631) -> 685.06776 | D631: =SUMIF(clean_data!$U:$U,$A631,clean_data!$AM:$AM) -> 1616102.7 | E631: =IF(A631=A630,E630+C631,C631) -> 1616102.7 | F631: =E631/D631 -> 1 | G631: =IF(F631<=0.8,"A",IF(F631<=0.95,"B","C")) -> C
